{"v":"4.8.0","meta":{"g":"LottieFiles AE ","a":"","k":"","d":"","tc":""},"fr":60,"ip":0,"op":598,"w":948,"h":548,"nm":"11","ddd":0,"assets":[],"layers":[{"ddd":0,"ind":1,"ty":4,"nm":"Layer 14","sr":1,"ks":{"o":{"a":1,"k":[{"i":{"x":[0.833],"y":[0.833]},"o":{"x":[0.167],"y":[0.167]},"t":111,"s":[0]},{"t":126,"s":[100]}],"ix":11},"r":{"a":0,"k":0,"ix":10},"p":{"a":1,"k":[{"i":{"x":0,"y":1},"o":{"x":0.167,"y":0},"t":101,"s":[225.515,-164.4,0],"to":[0,53.5,0],"ti":[0,-53.5,0]},{"t":144,"s":[225.515,156.6,0]}],"ix":2},"a":{"a":0,"k":[-256.485,-129.4,0],"ix":1},"s":{"a":0,"k":[100,100,100],"ix":6}},"ao":0,"shapes":[{"ty":"gr","it":[{"ind":0,"ty":"sh","ix":1,"ks":{"a":0,"k":{"i":[[0,0],[0,0],[0,0],[0,0],[0,0],[0,0],[0,0]],"o":[[0,0],[0,0],[0,0],[0,0],[0,0],[0,0],[0,0]],"v":[[-283.398,-123.608],[-256.478,-76.981],[-229.572,-123.608],[-247.509,-123.608],[-247.509,-181.818],[-265.461,-181.818],[-265.461,-123.608]],"c":true},"ix":2},"nm":"Path 1","mn":"ADBE Vector Shape - Group","hd":false},{"ty":"fl","c":{"a":0,"k":[0.607843160629,0.639215707779,1,1],"ix":4},"o":{"a":0,"k":100,"ix":5},"r":1,"bm":0,"nm":"Fill 1","mn":"ADBE Vector Graphic - Fill","hd":false},{"ty":"tr","p":{"a":0,"k":[0,0],"ix":2},"a":{"a":0,"k":[0,0],"ix":1},"s":{"a":0,"k":[100,100],"ix":3},"r":{"a":0,"k":0,"ix":6},"o":{"a":0,"k":100,"ix":7},"sk":{"a":0,"k":0,"ix":4},"sa":{"a":0,"k":0,"ix":5},"nm":"Transform"}],"nm":"Group 1","np":2,"cix":2,"bm":0,"ix":1,"mn":"ADBE Vector Group","hd":false}],"ip":0,"op":1200,"st":0,"bm":0},{"ddd":0,"ind":2,"ty":4,"nm":"Layer 13","sr":1,"ks":{"o":{"a":1,"k":[{"i":{"x":[0.833],"y":[0.833]},"o":{"x":[0.167],"y":[0.167]},"t":111,"s":[0]},{"t":126,"s":[100]}],"ix":11},"r":{"a":0,"k":0,"ix":10},"p":{"a":1,"k":[{"i":{"x":0,"y":1},"o":{"x":0.167,"y":0},"t":101,"s":[170.444,460.6,0],"to":[0,-50.667,0],"ti":[0,50.667,0]},{"t":144,"s":[170.444,156.6,0]}],"ix":2},"a":{"a":0,"k":[0,0,0],"ix":1},"s":{"a":0,"k":[100,100,100],"ix":6}},"ao":0,"shapes":[{"ty":"gr","it":[{"ind":0,"ty":"sh","ix":1,"ks":{"a":0,"k":{"i":[[0,0],[0,0],[0,0],[0,0],[0,0],[0,0],[0,0]],"o":[[0,0],[0,0],[0,0],[0,0],[0,0],[0,0],[0,0]],"v":[[26.913,-5.791],[0.007,-52.419],[-26.913,-5.791],[-8.977,-5.791],[-8.977,52.419],[8.977,52.419],[8.977,-5.791]],"c":true},"ix":2},"nm":"Path 1","mn":"ADBE Vector Shape - Group","hd":false},{"ty":"fl","c":{"a":0,"k":[0.482352942228,0.521568655968,0.988235294819,1],"ix":4},"o":{"a":0,"k":100,"ix":5},"r":1,"bm":0,"nm":"Fill 1","mn":"ADBE Vector Graphic - Fill","hd":false},{"ty":"tr","p":{"a":0,"k":[0,0],"ix":2},"a":{"a":0,"k":[0,0],"ix":1},"s":{"a":0,"k":[100,100],"ix":3},"r":{"a":0,"k":0,"ix":6},"o":{"a":0,"k":100,"ix":7},"sk":{"a":0,"k":0,"ix":4},"sa":{"a":0,"k":0,"ix":5},"nm":"Transform"}],"nm":"Group 1","np":2,"cix":2,"bm":0,"ix":1,"mn":"ADBE Vector Group","hd":false}],"ip":0,"op":1200,"st":0,"bm":0},{"ddd":0,"ind":3,"ty":4,"nm":"Merged Shape Layer","sr":1,"ks":{"o":{"a":0,"k":100,"ix":11},"r":{"a":0,"k":0,"ix":10},"p":{"a":0,"k":[782.769,344.489,0],"ix":2},"a":{"a":0,"k":[940.769,418.489,0],"ix":1},"s":{"a":0,"k":[100,100,100],"ix":6}},"ao":0,"shapes":[{"ty":"gr","it":[{"ty":"gr","it":[{"ind":0,"ty":"sh","ix":1,"ks":{"a":1,"k":[{"i":{"x":0.667,"y":1},"o":{"x":0.333,"y":0},"t":252,"s":[{"i":[[0,0],[0,0],[0,0],[0,0]],"o":[[0,0],[0,0],[0,0],[0,0]],"v":[[-59.407,-3.6],[-59.593,-3.6],[-59.593,3.6],[-59.407,3.6]],"c":true}]},{"t":275,"s":[{"i":[[0,0],[0,0],[0,0],[0,0]],"o":[[0,0],[0,0],[0,0],[0,0]],"v":[[59.593,-3.6],[-59.593,-3.6],[-59.593,3.6],[59.593,3.6]],"c":true}]}],"ix":2},"nm":"Path 1","mn":"ADBE Vector Shape - Group","hd":false},{"ty":"fl","c":{"a":0,"k":[1,1,1,1],"ix":4},"o":{"a":0,"k":100,"ix":5},"r":1,"bm":0,"nm":"Fill 1","mn":"ADBE Vector Graphic - Fill","hd":false},{"ty":"tr","p":{"a":0,"k":[0,0],"ix":2},"a":{"a":0,"k":[0,0],"ix":1},"s":{"a":0,"k":[100,100],"ix":3},"r":{"a":0,"k":0,"ix":6},"o":{"a":0,"k":100,"ix":7},"sk":{"a":0,"k":0,"ix":4},"sa":{"a":0,"k":0,"ix":5},"nm":"Transform"}],"nm":"Group 1","np":2,"cix":2,"bm":0,"ix":1,"mn":"ADBE Vector Group","hd":false},{"ty":"tr","p":{"a":0,"k":[927.698,452.478],"ix":2},"a":{"a":0,"k":[0,0],"ix":1},"s":{"a":0,"k":[100,100],"ix":3},"r":{"a":0,"k":0,"ix":6},"o":{"a":0,"k":100,"ix":7},"sk":{"a":0,"k":0,"ix":4},"sa":{"a":0,"k":0,"ix":5},"nm":"Transform"}],"nm":"Layer 26","np":1,"cix":2,"bm":0,"ix":1,"mn":"ADBE Vector Group","hd":false},{"ty":"gr","it":[{"ty":"gr","it":[{"ind":0,"ty":"sh","ix":1,"ks":{"a":1,"k":[{"i":{"x":0.667,"y":1},"o":{"x":0.333,"y":0},"t":252,"s":[{"i":[[0,0],[0,0],[0,0],[0,0]],"o":[[0,0],[0,0],[0,0],[0,0]],"v":[[-66.944,-3.725],[-67.056,-3.6],[-67.056,3.6],[-66.944,3.475]],"c":true}]},{"t":264,"s":[{"i":[[0,0],[0,0],[0,0],[0,0]],"o":[[0,0],[0,0],[0,0],[0,0]],"v":[[67.056,-3.6],[-67.056,-3.6],[-67.056,3.6],[67.056,3.6]],"c":true}]}],"ix":2},"nm":"Path 1","mn":"ADBE Vector Shape - Group","hd":false},{"ty":"fl","c":{"a":0,"k":[1,1,1,1],"ix":4},"o":{"a":0,"k":100,"ix":5},"r":1,"bm":0,"nm":"Fill 1","mn":"ADBE Vector Graphic - Fill","hd":false},{"ty":"tr","p":{"a":0,"k":[0,0],"ix":2},"a":{"a":0,"k":[0,0],"ix":1},"s":{"a":0,"k":[100,100],"ix":3},"r":{"a":0,"k":0,"ix":6},"o":{"a":0,"k":100,"ix":7},"sk":{"a":0,"k":0,"ix":4},"sa":{"a":0,"k":0,"ix":5},"nm":"Transform"}],"nm":"Group 1","np":2,"cix":2,"bm":0,"ix":1,"mn":"ADBE Vector Group","hd":false},{"ty":"tr","p":{"a":0,"k":[935.161,438.893],"ix":2},"a":{"a":0,"k":[0,0],"ix":1},"s":{"a":0,"k":[100,100],"ix":3},"r":{"a":0,"k":0,"ix":6},"o":{"a":0,"k":100,"ix":7},"sk":{"a":0,"k":0,"ix":4},"sa":{"a":0,"k":0,"ix":5},"nm":"Transform"}],"nm":"Layer 25","np":1,"cix":2,"bm":0,"ix":2,"mn":"ADBE Vector Group","hd":false},{"ty":"gr","it":[{"ty":"gr","it":[{"ind":0,"ty":"sh","ix":1,"ks":{"a":1,"k":[{"i":{"x":0.667,"y":1},"o":{"x":0.333,"y":0},"t":252,"s":[{"i":[[0,0],[0,0],[0,0],[0,0]],"o":[[0,0],[0,0],[0,0],[0,0]],"v":[[-72.711,-3.475],[-72.664,-3.6],[-72.664,3.6],[-72.711,3.725]],"c":true}]},{"t":273,"s":[{"i":[[0,0],[0,0],[0,0],[0,0]],"o":[[0,0],[0,0],[0,0],[0,0]],"v":[[72.664,-3.6],[-72.664,-3.6],[-72.664,3.6],[72.664,3.6]],"c":true}]}],"ix":2},"nm":"Path 1","mn":"ADBE Vector Shape - Group","hd":false},{"ty":"fl","c":{"a":0,"k":[1,1,1,1],"ix":4},"o":{"a":0,"k":100,"ix":5},"r":1,"bm":0,"nm":"Fill 1","mn":"ADBE Vector Graphic - Fill","hd":false},{"ty":"tr","p":{"a":0,"k":[0,0],"ix":2},"a":{"a":0,"k":[0,0],"ix":1},"s":{"a":0,"k":[100,100],"ix":3},"r":{"a":0,"k":0,"ix":6},"o":{"a":0,"k":100,"ix":7},"sk":{"a":0,"k":0,"ix":4},"sa":{"a":0,"k":0,"ix":5},"nm":"Transform"}],"nm":"Group 1","np":2,"cix":2,"bm":0,"ix":1,"mn":"ADBE Vector Group","hd":false},{"ty":"tr","p":{"a":0,"k":[940.769,425.306],"ix":2},"a":{"a":0,"k":[0,0],"ix":1},"s":{"a":0,"k":[100,100],"ix":3},"r":{"a":0,"k":0,"ix":6},"o":{"a":0,"k":100,"ix":7},"sk":{"a":0,"k":0,"ix":4},"sa":{"a":0,"k":0,"ix":5},"nm":"Transform"}],"nm":"Layer 24","np":1,"cix":2,"bm":0,"ix":3,"mn":"ADBE Vector Group","hd":false},{"ty":"gr","it":[{"ty":"gr","it":[{"ind":0,"ty":"sh","ix":1,"ks":{"a":1,"k":[{"i":{"x":0.667,"y":1},"o":{"x":0.333,"y":0},"t":252,"s":[{"i":[[0,0],[0,0],[0,0],[0,0]],"o":[[0,0],[0,0],[0,0],[0,0]],"v":[[-62.082,-3.6],[-62.168,-3.6],[-62.168,3.6],[-62.082,3.6]],"c":true}]},{"t":273,"s":[{"i":[[0,0],[0,0],[0,0],[0,0]],"o":[[0,0],[0,0],[0,0],[0,0]],"v":[[62.168,-3.6],[-62.168,-3.6],[-62.168,3.6],[62.168,3.6]],"c":true}]}],"ix":2},"nm":"Path 1","mn":"ADBE Vector Shape - Group","hd":false},{"ty":"fl","c":{"a":0,"k":[1,1,1,1],"ix":4},"o":{"a":0,"k":100,"ix":5},"r":1,"bm":0,"nm":"Fill 1","mn":"ADBE Vector Graphic - Fill","hd":false},{"ty":"tr","p":{"a":0,"k":[0,0],"ix":2},"a":{"a":0,"k":[0,0],"ix":1},"s":{"a":0,"k":[100,100],"ix":3},"r":{"a":0,"k":0,"ix":6},"o":{"a":0,"k":100,"ix":7},"sk":{"a":0,"k":0,"ix":4},"sa":{"a":0,"k":0,"ix":5},"nm":"Transform"}],"nm":"Group 1","np":2,"cix":2,"bm":0,"ix":1,"mn":"ADBE Vector Group","hd":false},{"ty":"tr","p":{"a":0,"k":[930.273,411.881],"ix":2},"a":{"a":0,"k":[0,0],"ix":1},"s":{"a":0,"k":[100,100],"ix":3},"r":{"a":0,"k":0,"ix":6},"o":{"a":0,"k":100,"ix":7},"sk":{"a":0,"k":0,"ix":4},"sa":{"a":0,"k":0,"ix":5},"nm":"Transform"}],"nm":"Layer 23","np":1,"cix":2,"bm":0,"ix":4,"mn":"ADBE Vector Group","hd":false},{"ty":"gr","it":[{"ty":"gr","it":[{"ind":0,"ty":"sh","ix":1,"ks":{"a":1,"k":[{"i":{"x":0.667,"y":1},"o":{"x":0.333,"y":0},"t":252,"s":[{"i":[[0,0],[0,0],[0,0],[0,0]],"o":[[0,0],[0,0],[0,0],[0,0]],"v":[[-50.763,-3.6],[-50.799,-3.6],[-50.799,3.6],[-50.763,3.6]],"c":true}]},{"t":267,"s":[{"i":[[0,0],[0,0],[0,0],[0,0]],"o":[[0,0],[0,0],[0,0],[0,0]],"v":[[50.799,-3.6],[-50.799,-3.6],[-50.799,3.6],[50.799,3.6]],"c":true}]}],"ix":2},"nm":"Path 1","mn":"ADBE Vector Shape - Group","hd":false},{"ty":"fl","c":{"a":0,"k":[1,1,1,1],"ix":4},"o":{"a":0,"k":100,"ix":5},"r":1,"bm":0,"nm":"Fill 1","mn":"ADBE Vector Graphic - Fill","hd":false},{"ty":"tr","p":{"a":0,"k":[0,0],"ix":2},"a":{"a":0,"k":[0,0],"ix":1},"s":{"a":0,"k":[100,100],"ix":3},"r":{"a":0,"k":0,"ix":6},"o":{"a":0,"k":100,"ix":7},"sk":{"a":0,"k":0,"ix":4},"sa":{"a":0,"k":0,"ix":5},"nm":"Transform"}],"nm":"Group 1","np":2,"cix":2,"bm":0,"ix":1,"mn":"ADBE Vector Group","hd":false},{"ty":"tr","p":{"a":0,"k":[918.904,398.19],"ix":2},"a":{"a":0,"k":[0,0],"ix":1},"s":{"a":0,"k":[100,100],"ix":3},"r":{"a":0,"k":0,"ix":6},"o":{"a":0,"k":100,"ix":7},"sk":{"a":0,"k":0,"ix":4},"sa":{"a":0,"k":0,"ix":5},"nm":"Transform"}],"nm":"Layer 22","np":1,"cix":2,"bm":0,"ix":5,"mn":"ADBE Vector Group","hd":false},{"ty":"gr","it":[{"ty":"gr","it":[{"ind":0,"ty":"sh","ix":1,"ks":{"a":1,"k":[{"i":{"x":0.667,"y":1},"o":{"x":0.333,"y":0},"t":252,"s":[{"i":[[0,0],[0,0],[0,0],[0,0]],"o":[[0,0],[0,0],[0,0],[0,0]],"v":[[-72.711,-3.5],[-72.664,-3.6],[-72.664,3.6],[-72.711,3.7]],"c":true}]},{"t":275,"s":[{"i":[[0,0],[0,0],[0,0],[0,0]],"o":[[0,0],[0,0],[0,0],[0,0]],"v":[[72.664,-3.6],[-72.664,-3.6],[-72.664,3.6],[72.664,3.6]],"c":true}]}],"ix":2},"nm":"Path 1","mn":"ADBE Vector Shape - Group","hd":false},{"ty":"fl","c":{"a":0,"k":[1,1,1,1],"ix":4},"o":{"a":0,"k":100,"ix":5},"r":1,"bm":0,"nm":"Fill 1","mn":"ADBE Vector Graphic - Fill","hd":false},{"ty":"tr","p":{"a":0,"k":[0,0],"ix":2},"a":{"a":0,"k":[0,0],"ix":1},"s":{"a":0,"k":[100,100],"ix":3},"r":{"a":0,"k":0,"ix":6},"o":{"a":0,"k":100,"ix":7},"sk":{"a":0,"k":0,"ix":4},"sa":{"a":0,"k":0,"ix":5},"nm":"Transform"}],"nm":"Group 1","np":2,"cix":2,"bm":0,"ix":1,"mn":"ADBE Vector Group","hd":false},{"ty":"tr","p":{"a":0,"k":[940.769,384.5],"ix":2},"a":{"a":0,"k":[0,0],"ix":1},"s":{"a":0,"k":[100,100],"ix":3},"r":{"a":0,"k":0,"ix":6},"o":{"a":0,"k":100,"ix":7},"sk":{"a":0,"k":0,"ix":4},"sa":{"a":0,"k":0,"ix":5},"nm":"Transform"}],"nm":"Layer 21","np":1,"cix":2,"bm":0,"ix":6,"mn":"ADBE Vector Group","hd":false}],"ip":252,"op":1200,"st":0,"bm":0},{"ddd":0,"ind":4,"ty":4,"nm":"Layer 20","sr":1,"ks":{"o":{"a":0,"k":100,"ix":11},"r":{"a":0,"k":0,"ix":10},"p":{"a":0,"k":[785.284,345.362,0],"ix":2},"a":{"a":0,"k":[0,0,0],"ix":1},"s":{"a":0,"k":[100,100,100],"ix":6}},"ao":0,"shapes":[{"ty":"gr","it":[{"ind":0,"ty":"sh","ix":1,"ks":{"a":1,"k":[{"i":{"x":0.667,"y":1},"o":{"x":0.333,"y":0},"t":213,"s":[{"i":[[0,0],[0,0],[0,0],[0,0]],"o":[[0,0],[0,0],[0,0],[0,0]],"v":[[-87.315,-51.333],[-87.31,-51.333],[-87.31,51.333],[-87.315,51.333]],"c":true}]},{"t":252,"s":[{"i":[[0,0],[0,0],[0,0],[0,0]],"o":[[0,0],[0,0],[0,0],[0,0]],"v":[[-87.315,-51.333],[87.315,-51.333],[87.315,51.333],[-87.315,51.333]],"c":true}]}],"ix":2},"nm":"Path 1","mn":"ADBE Vector Shape - Group","hd":false},{"ty":"fl","c":{"a":0,"k":[0.686274528503,0.713725507259,1,1],"ix":4},"o":{"a":0,"k":100,"ix":5},"r":1,"bm":0,"nm":"Fill 1","mn":"ADBE Vector Graphic - Fill","hd":false},{"ty":"tr","p":{"a":0,"k":[0,0],"ix":2},"a":{"a":0,"k":[0,0],"ix":1},"s":{"a":0,"k":[100,100],"ix":3},"r":{"a":0,"k":0,"ix":6},"o":{"a":0,"k":100,"ix":7},"sk":{"a":0,"k":0,"ix":4},"sa":{"a":0,"k":0,"ix":5},"nm":"Transform"}],"nm":"Group 1","np":2,"cix":2,"bm":0,"ix":1,"mn":"ADBE Vector Group","hd":false}],"ip":213,"op":1200,"st":0,"bm":0},{"ddd":0,"ind":5,"ty":4,"nm":"Layer 19","sr":1,"ks":{"o":{"a":0,"k":100,"ix":11},"r":{"a":0,"k":0,"ix":10},"p":{"a":0,"k":[802.008,448.459,0],"ix":2},"a":{"a":0,"k":[0,0,0],"ix":1},"s":{"a":0,"k":[100,100,100],"ix":6}},"ao":0,"shapes":[{"ty":"gr","it":[{"ind":0,"ty":"sh","ix":1,"ks":{"a":0,"k":{"i":[[1.981,-0.004],[0,0],[1.13,2.834],[2.565,1.653],[3.048,-0.141],[2.401,-1.882],[2.675,1.494],[3.044,-0.342],[2.277,-2.05],[0.66,-2.992],[2.168,-0.232],[1.858,-1.141],[1.189,-1.827],[0.29,-2.16],[0,0],[1.715,-0.996],[0.981,-1.724],[-0.001,-0.236],[-0.119,-0.204],[-0.204,-0.117],[-0.236,0],[0,0],[-0.204,0.118],[-0.118,0.204],[-0.001,0.236],[0.118,0.204],[1.714,0.992]],"o":[[0,0],[0.723,-2.964],[-1.13,-2.834],[-2.565,-1.653],[-3.048,0.14],[-1.307,-2.771],[-2.675,-1.494],[-3.045,0.341],[-2.278,2.049],[-2.058,-0.72],[-2.167,0.233],[-1.858,1.14],[-1.189,1.827],[0,0],[-1.983,-0.001],[-1.714,0.996],[-0.117,0.204],[0.001,0.236],[0.118,0.204],[0.205,0.118],[0,0],[0.236,0],[0.205,-0.117],[0.119,-0.204],[0,-0.236],[-0.983,-1.72],[-1.715,-0.992]],"v":[[35.442,7.894],[35.028,7.894],[34.402,-1.021],[28.721,-7.92],[20.092,-10.245],[11.714,-7.135],[5.592,-13.693],[-3.203,-15.465],[-11.387,-11.789],[-15.905,-4.038],[-22.323,-4.778],[-28.437,-2.692],[-33.065,1.815],[-35.312,7.871],[-35.442,7.871],[-41.088,9.39],[-45.203,13.543],[-45.381,14.215],[-45.199,14.886],[-44.707,15.377],[-44.034,15.556],[44.034,15.556],[44.706,15.377],[45.199,14.886],[45.381,14.215],[45.202,13.543],[41.084,9.403]],"c":true},"ix":2},"nm":"Path 1","mn":"ADBE Vector Shape - Group","hd":false},{"ty":"fl","c":{"a":0,"k":[0.949019610882,0.952941179276,1,1],"ix":4},"o":{"a":0,"k":100,"ix":5},"r":1,"bm":0,"nm":"Fill 1","mn":"ADBE Vector Graphic - Fill","hd":false},{"ty":"tr","p":{"a":0,"k":[0,0],"ix":2},"a":{"a":0,"k":[0,0],"ix":1},"s":{"a":0,"k":[100,100],"ix":3},"r":{"a":0,"k":0,"ix":6},"o":{"a":0,"k":100,"ix":7},"sk":{"a":0,"k":0,"ix":4},"sa":{"a":0,"k":0,"ix":5},"nm":"Transform"}],"nm":"Group 1","np":2,"cix":2,"bm":0,"ix":1,"mn":"ADBE Vector Group","hd":false}],"ip":0,"op":1200,"st":0,"bm":0},{"ddd":0,"ind":6,"ty":4,"nm":"Layer 18","sr":1,"ks":{"o":{"a":0,"k":100,"ix":11},"r":{"a":0,"k":0,"ix":10},"p":{"a":0,"k":[720.461,176.43,0],"ix":2},"a":{"a":0,"k":[238.461,-109.57,0],"ix":1},"s":{"a":1,"k":[{"i":{"x":[0,0,0.667],"y":[1,1,1]},"o":{"x":[0.142,0.142,0.333],"y":[0,0,0]},"t":227,"s":[0,0,100]},{"t":265,"s":[100,100,100]}],"ix":6}},"ao":0,"shapes":[{"ty":"gr","it":[{"ind":0,"ty":"sh","ix":1,"ks":{"a":0,"k":{"i":[[-0.322,-0.004],[-0.284,-0.282],[-1.002,-1.02],[0.424,-0.672],[1.34,-2.114],[0.444,-0.09],[0.742,-0.119],[0.226,-0.227],[5.407,-5.427],[0.287,0.294],[1.425,1.403],[-0.263,0.263],[-5.433,5.424],[-0.051,0.327],[-0.136,0.724],[-0.418,0.265],[-2.086,1.327]],"o":[[0.406,0.004],[1.012,1.011],[0.556,0.566],[-1.336,2.117],[-0.246,0.388],[-0.737,0.149],[-0.327,0.053],[-5.413,5.421],[-0.282,0.283],[-1.396,-1.432],[-0.249,-0.245],[5.438,-5.419],[0.226,-0.226],[0.117,-0.727],[0.09,-0.481],[2.088,-1.322],[0.264,-0.167]],"v":[[257.581,-133.211],[258.608,-132.76],[261.64,-129.723],[261.834,-127.882],[257.808,-121.543],[256.77,-120.844],[254.557,-120.408],[253.77,-119.988],[237.529,-103.726],[236.826,-103.721],[232.587,-107.966],[232.579,-108.6],[248.873,-124.874],[249.295,-125.659],[249.724,-127.828],[250.463,-128.941],[256.721,-132.919]],"c":true},"ix":2},"nm":"Path 1","mn":"ADBE Vector Shape - Group","hd":false},{"ty":"fl","c":{"a":0,"k":[1,1,1,1],"ix":4},"o":{"a":0,"k":100,"ix":5},"r":1,"bm":0,"nm":"Fill 1","mn":"ADBE Vector Graphic - Fill","hd":false},{"ty":"tr","p":{"a":0,"k":[0,0],"ix":2},"a":{"a":0,"k":[0,0],"ix":1},"s":{"a":0,"k":[100,100],"ix":3},"r":{"a":0,"k":0,"ix":6},"o":{"a":0,"k":100,"ix":7},"sk":{"a":0,"k":0,"ix":4},"sa":{"a":0,"k":0,"ix":5},"nm":"Transform"}],"nm":"Group 1","np":2,"cix":2,"bm":0,"ix":1,"mn":"ADBE Vector Group","hd":false},{"ty":"gr","it":[{"ind":0,"ty":"sh","ix":1,"ks":{"a":0,"k":{"i":[[0,0.431],[-0.025,0.109],[-0.893,-0.738],[-0.879,-0.768],[-0.253,0.265],[-0.836,0.793],[0.206,0.235],[0.745,0.86],[-0.227,0.576],[-0.593,0.072],[-0.995,-4.078],[0.313,-1.245],[-0.196,-0.194],[-1.88,-1.862],[0.239,-0.236],[1.664,-1.686],[0.199,0.201],[1.865,1.878],[0.297,-0.07],[0.706,4.655],[0.11,0.049],[0,0.061],[0.076,0.184]],"o":[[0.152,-0.068],[0.26,-1.126],[0.9,0.745],[0.234,0.205],[0.793,-0.837],[0.264,-0.25],[-0.75,-0.856],[-0.396,-0.457],[0.229,-0.581],[4.261,-0.512],[0.304,1.246],[-0.07,0.281],[1.878,1.864],[0.222,0.219],[-1.687,1.664],[-0.224,0.227],[-1.865,-1.877],[-0.206,-0.21],[-4.581,1.084],[-0.014,-0.086],[0,-0.062],[0.076,-0.185],[0,-0.432]],"v":[[214.815,-126.194],[214.927,-126.518],[217.245,-127.317],[219.914,-125.046],[220.534,-125.049],[222.98,-127.496],[222.988,-128.115],[220.769,-130.709],[220.449,-132.241],[221.74,-133.128],[230.737,-127.033],[230.736,-123.29],[230.927,-122.647],[236.549,-117.043],[236.56,-116.477],[231.535,-111.452],[231.005,-111.466],[225.398,-117.085],[224.718,-117.285],[214.907,-123.923],[214.815,-124.161],[214.815,-124.346],[214.815,-124.9]],"c":true},"ix":2},"nm":"Path 1","mn":"ADBE Vector Shape - Group","hd":false},{"ty":"fl","c":{"a":0,"k":[1,1,1,1],"ix":4},"o":{"a":0,"k":100,"ix":5},"r":1,"bm":0,"nm":"Fill 1","mn":"ADBE Vector Graphic - Fill","hd":false},{"ty":"tr","p":{"a":0,"k":[0,0],"ix":2},"a":{"a":0,"k":[0,0],"ix":1},"s":{"a":0,"k":[100,100],"ix":3},"r":{"a":0,"k":0,"ix":6},"o":{"a":0,"k":100,"ix":7},"sk":{"a":0,"k":0,"ix":4},"sa":{"a":0,"k":0,"ix":5},"nm":"Transform"}],"nm":"Group 2","np":2,"cix":2,"bm":0,"ix":2,"mn":"ADBE Vector Group","hd":false},{"ty":"gr","it":[{"ind":0,"ty":"sh","ix":1,"ks":{"a":0,"k":{"i":[[0.616,0],[0.745,0.333],[-0.899,3.763],[0.211,0.208],[1.868,1.851],[-0.263,0.258],[-1.653,1.676],[-0.222,-0.224],[-1.84,-1.858],[-0.353,0.078],[0.888,-5.66],[0.923,0.763],[0.893,0.776],[0.221,-0.229],[0.854,-0.821],[-0.18,-0.207],[-0.74,-0.844],[0.245,-0.617],[0.632,-0.029],[0.031,-0.099]],"o":[[-0.768,-0.233],[-3.537,-1.586],[0.071,-0.297],[-1.868,-1.852],[-0.227,-0.226],[1.68,-1.649],[0.232,-0.236],[1.839,1.859],[0.242,0.245],[5.583,-1.254],[-0.184,1.182],[-0.912,-0.754],[-0.205,-0.179],[-0.821,0.854],[-0.226,0.218],[0.736,0.847],[0.419,0.476],[-0.246,0.618],[-0.072,0.004],[-0.615,-0.001]],"v":[[253.051,-85.93],[250.741,-86.622],[246.171,-95.831],[245.976,-96.513],[240.387,-102.084],[240.371,-102.682],[245.366,-107.673],[245.931,-107.665],[251.467,-102.107],[252.265,-101.874],[262,-92.72],[259.674,-91.825],[256.971,-94.127],[256.421,-94.125],[253.908,-91.613],[253.9,-91.064],[256.089,-88.505],[256.468,-86.902],[255.085,-86.013],[254.898,-85.929]],"c":true},"ix":2},"nm":"Path 1","mn":"ADBE Vector Shape - Group","hd":false},{"ty":"fl","c":{"a":0,"k":[1,1,1,1],"ix":4},"o":{"a":0,"k":100,"ix":5},"r":1,"bm":0,"nm":"Fill 1","mn":"ADBE Vector Graphic - Fill","hd":false},{"ty":"tr","p":{"a":0,"k":[0,0],"ix":2},"a":{"a":0,"k":[0,0],"ix":1},"s":{"a":0,"k":[100,100],"ix":3},"r":{"a":0,"k":0,"ix":6},"o":{"a":0,"k":100,"ix":7},"sk":{"a":0,"k":0,"ix":4},"sa":{"a":0,"k":0,"ix":5},"nm":"Transform"}],"nm":"Group 3","np":2,"cix":2,"bm":0,"ix":3,"mn":"ADBE Vector Group","hd":false},{"ty":"gr","it":[{"ind":0,"ty":"sh","ix":1,"ks":{"a":0,"k":{"i":[[0.286,-0.467],[0.107,-0.108],[2.257,-2.264],[0.563,0.122],[-0.67,0.823],[-0.141,0.142],[-2.181,2.187],[-0.468,-0.007],[-0.262,-0.473]],"o":[[-0.078,0.129],[-2.259,2.261],[-0.394,0.395],[-1.031,-0.224],[0.124,-0.155],[2.184,-2.184],[0.315,-0.315],[0.533,0.008],[0.271,0.488]],"v":[[228.919,-98.118],[228.62,-97.77],[221.841,-90.988],[220.437,-90.484],[219.67,-92.729],[220.086,-93.16],[226.637,-99.714],[227.762,-100.26],[228.97,-99.559]],"c":true},"ix":2},"nm":"Path 1","mn":"ADBE Vector Shape - Group","hd":false},{"ind":1,"ty":"sh","ix":2,"ks":{"a":0,"k":{"i":[[0.569,0.572],[3.477,3.466],[0.532,-0.547],[-0.578,-0.555],[0.255,-0.255],[2.892,-2.896],[0.347,-0.975],[-0.005,-0.998],[-0.02,-0.114],[-0.022,-0.08],[-0.227,-0.512],[-0.31,-0.429],[-0.735,-0.446],[-0.884,-0.192],[-0.56,0.006],[-0.096,0.01],[-0.1,0.021],[-0.7,0.377],[-0.3,0.229],[-0.157,0],[-2.843,2.859],[-0.288,-0.301],[-0.548,0.53]],"o":[[-3.466,-3.477],[-0.57,-0.569],[-0.533,0.548],[0.294,0.282],[-2.903,2.885],[-0.73,0.73],[-0.336,0.946],[0.001,0.116],[0.013,0.081],[0.15,0.541],[0.214,0.485],[0.504,0.697],[0.777,0.47],[0.516,0.112],[0.096,-0.002],[0.101,-0.011],[0.773,-0.159],[0.332,-0.178],[0.156,-0.119],[2.843,-2.859],[0.248,-0.248],[0.557,0.581],[0.551,-0.53]],"v":[[237.967,-98.663],[227.553,-109.077],[225.568,-109.086],[225.6,-107.144],[225.58,-106.476],[216.892,-97.797],[215.229,-95.219],[214.809,-92.272],[214.831,-91.925],[214.889,-91.685],[215.394,-90.089],[216.185,-88.714],[218.064,-86.981],[220.581,-86.026],[222.199,-85.943],[222.488,-85.956],[222.789,-86.007],[224.995,-86.745],[225.943,-87.359],[226.815,-88.126],[235.36,-96.688],[236.026,-96.717],[237.968,-96.677]],"c":true},"ix":2},"nm":"Path 2","mn":"ADBE Vector Shape - Group","hd":false},{"ty":"fl","c":{"a":0,"k":[1,1,1,1],"ix":4},"o":{"a":0,"k":100,"ix":5},"r":1,"bm":0,"nm":"Fill 1","mn":"ADBE Vector Graphic - Fill","hd":false},{"ty":"tr","p":{"a":0,"k":[0,0],"ix":2},"a":{"a":0,"k":[0,0],"ix":1},"s":{"a":0,"k":[100,100],"ix":3},"r":{"a":0,"k":0,"ix":6},"o":{"a":0,"k":100,"ix":7},"sk":{"a":0,"k":0,"ix":4},"sa":{"a":0,"k":0,"ix":5},"nm":"Transform"}],"nm":"Group 4","np":3,"cix":2,"bm":0,"ix":4,"mn":"ADBE Vector Group","hd":false},{"ty":"gr","it":[{"ind":0,"ty":"sh","ix":1,"ks":{"a":0,"k":{"i":[[-21.861,21.861],[21.862,21.861],[21.861,-21.862],[-21.862,-21.862]],"o":[[21.862,-21.862],[-21.861,-21.862],[-21.862,21.861],[21.861,21.861]],"v":[[278.044,-69.986],[278.044,-149.154],[198.877,-149.154],[198.877,-69.986]],"c":true},"ix":2},"nm":"Path 1","mn":"ADBE Vector Shape - Group","hd":false},{"ty":"fl","c":{"a":0,"k":[0.482352942228,0.521568655968,0.988235294819,1],"ix":4},"o":{"a":0,"k":100,"ix":5},"r":1,"bm":0,"nm":"Fill 1","mn":"ADBE Vector Graphic - Fill","hd":false},{"ty":"tr","p":{"a":0,"k":[0,0],"ix":2},"a":{"a":0,"k":[0,0],"ix":1},"s":{"a":0,"k":[100,100],"ix":3},"r":{"a":0,"k":0,"ix":6},"o":{"a":0,"k":100,"ix":7},"sk":{"a":0,"k":0,"ix":4},"sa":{"a":0,"k":0,"ix":5},"nm":"Transform"}],"nm":"Group 5","np":2,"cix":2,"bm":0,"ix":5,"mn":"ADBE Vector Group","hd":false}],"ip":0,"op":1200,"st":0,"bm":0},{"ddd":0,"ind":7,"ty":4,"nm":"Layer 15","sr":1,"ks":{"o":{"a":0,"k":100,"ix":11},"r":{"a":0,"k":0,"ix":10},"p":{"a":0,"k":[834.872,145.386,0],"ix":2},"a":{"a":0,"k":[0,0,0],"ix":1},"s":{"a":0,"k":[100,100,100],"ix":6}},"ao":0,"shapes":[{"ty":"gr","it":[{"ind":0,"ty":"sh","ix":1,"ks":{"a":0,"k":{"i":[[3.961,-0.008],[0,0],[2.26,5.669],[5.129,3.307],[6.097,-0.282],[4.803,-3.765],[5.35,2.988],[6.089,-0.683],[4.556,-4.098],[1.32,-5.984],[4.336,-0.466],[3.716,-2.28],[2.379,-3.654],[0.58,-4.321],[0,0],[3.429,-1.993],[1.961,-3.448],[-0.001,-0.472],[-0.236,-0.408],[-0.409,-0.235],[-0.472,0.001],[0,0],[-0.409,0.235],[-0.237,0.408],[-0.001,0.472],[0.235,0.409],[3.429,1.984]],"o":[[0,0],[1.446,-5.929],[-2.261,-5.669],[-5.13,-3.307],[-6.096,0.281],[-2.613,-5.543],[-5.35,-2.988],[-6.09,0.683],[-4.555,4.098],[-4.116,-1.44],[-4.335,0.465],[-3.716,2.281],[-2.378,3.655],[0,0],[-3.966,-0.003],[-3.429,1.992],[-0.235,0.409],[0.001,0.472],[0.237,0.408],[0.409,0.235],[0,0],[0.472,0.001],[0.41,-0.235],[0.237,-0.408],[0.001,-0.472],[-1.966,-3.439],[-3.429,-1.985]],"v":[[70.886,15.789],[70.058,15.789],[68.806,-2.041],[57.444,-15.84],[40.185,-20.49],[23.429,-14.269],[11.185,-27.386],[-6.405,-30.93],[-22.775,-23.578],[-31.809,-8.075],[-44.645,-9.554],[-56.874,-5.384],[-66.13,3.63],[-70.624,15.744],[-70.884,15.744],[-82.176,18.781],[-90.405,27.087],[-90.762,28.431],[-90.4,29.774],[-89.413,30.756],[-88.069,31.113],[88.069,31.113],[89.413,30.756],[90.4,29.774],[90.762,28.431],[90.405,27.087],[82.168,18.807]],"c":true},"ix":2},"nm":"Path 1","mn":"ADBE Vector Shape - Group","hd":false},{"ty":"fl","c":{"a":0,"k":[0.949019610882,0.952941179276,1,1],"ix":4},"o":{"a":0,"k":100,"ix":5},"r":1,"bm":0,"nm":"Fill 1","mn":"ADBE Vector Graphic - Fill","hd":false},{"ty":"tr","p":{"a":0,"k":[0,0],"ix":2},"a":{"a":0,"k":[0,0],"ix":1},"s":{"a":0,"k":[100,100],"ix":3},"r":{"a":0,"k":0,"ix":6},"o":{"a":0,"k":100,"ix":7},"sk":{"a":0,"k":0,"ix":4},"sa":{"a":0,"k":0,"ix":5},"nm":"Transform"}],"nm":"Group 1","np":2,"cix":2,"bm":0,"ix":1,"mn":"ADBE Vector Group","hd":false}],"ip":0,"op":1200,"st":0,"bm":0},{"ddd":0,"ind":8,"ty":4,"nm":"Layer 12","sr":1,"ks":{"o":{"a":0,"k":100,"ix":11},"r":{"a":0,"k":0,"ix":10},"p":{"a":0,"k":[197.359,95.705,0],"ix":2},"a":{"a":0,"k":[0,0,0],"ix":1},"s":{"a":0,"k":[100,100,100],"ix":6}},"ao":0,"shapes":[{"ty":"gr","it":[{"ind":0,"ty":"sh","ix":1,"ks":{"a":0,"k":{"i":[[5.373,-0.011],[0,0],[3.067,7.688],[6.957,4.485],[8.268,-0.382],[6.514,-5.107],[7.256,4.052],[8.259,-0.926],[6.179,-5.558],[1.791,-8.115],[5.88,-0.632],[5.04,-3.093],[3.226,-4.956],[0.787,-5.861],[0,0],[4.651,-2.702],[2.66,-4.675],[-0.001,-0.64],[-0.321,-0.554],[-0.555,-0.319],[-0.64,0.001],[0,0],[-0.555,0.319],[-0.321,0.553],[-0.002,0.64],[0.318,0.555],[4.65,2.691]],"o":[[0,0],[1.961,-8.041],[-3.066,-7.688],[-6.957,-4.484],[-8.268,0.382],[-3.544,-7.517],[-7.256,-4.052],[-8.259,0.926],[-6.178,5.558],[-5.582,-1.952],[-5.88,0.631],[-5.04,3.093],[-3.226,4.956],[0,0],[-5.379,-0.005],[-4.651,2.702],[-0.318,0.555],[0.001,0.64],[0.321,0.553],[0.555,0.319],[0,0],[0.64,0.001],[0.555,-0.319],[0.321,-0.554],[0.001,-0.64],[-2.668,-4.664],[-4.651,-2.691]],"v":[[96.138,21.414],[95.015,21.414],[93.316,-2.769],[77.907,-21.483],[54.5,-27.79],[31.774,-19.352],[15.168,-37.142],[-8.689,-41.949],[-30.889,-31.978],[-43.143,-10.953],[-60.551,-12.959],[-77.136,-7.302],[-89.69,4.923],[-95.785,21.352],[-96.138,21.352],[-111.452,25.471],[-122.613,36.736],[-123.097,38.559],[-122.605,40.381],[-121.268,41.712],[-119.444,42.197],[119.444,42.197],[121.267,41.712],[122.604,40.381],[123.097,38.559],[122.613,36.736],[111.441,25.506]],"c":true},"ix":2},"nm":"Path 1","mn":"ADBE Vector Shape - Group","hd":false},{"ty":"fl","c":{"a":0,"k":[0.949019610882,0.952941179276,1,1],"ix":4},"o":{"a":0,"k":100,"ix":5},"r":1,"bm":0,"nm":"Fill 1","mn":"ADBE Vector Graphic - Fill","hd":false},{"ty":"tr","p":{"a":0,"k":[0,0],"ix":2},"a":{"a":0,"k":[0,0],"ix":1},"s":{"a":0,"k":[100,100],"ix":3},"r":{"a":0,"k":0,"ix":6},"o":{"a":0,"k":100,"ix":7},"sk":{"a":0,"k":0,"ix":4},"sa":{"a":0,"k":0,"ix":5},"nm":"Transform"}],"nm":"Group 1","np":2,"cix":2,"bm":0,"ix":1,"mn":"ADBE Vector Group","hd":false}],"ip":0,"op":1200,"st":0,"bm":0},{"ddd":0,"ind":9,"ty":4,"nm":"Layer 17","sr":1,"ks":{"o":{"a":0,"k":100,"ix":11},"r":{"a":0,"k":0,"ix":10},"p":{"a":0,"k":[524.85,103.523,0],"ix":2},"a":{"a":0,"k":[42.85,-182.477,0],"ix":1},"s":{"a":1,"k":[{"i":{"x":[0,0,0.667],"y":[1,1,1]},"o":{"x":[0.142,0.142,0.333],"y":[0,0,0]},"t":207,"s":[0,0,100]},{"t":245,"s":[100,100,100]}],"ix":6}},"ao":0,"shapes":[{"ty":"gr","it":[{"ind":0,"ty":"sh","ix":1,"ks":{"a":0,"k":{"i":[[0,0],[0,0],[0,0],[0,0],[0,0],[0,0],[0,0]],"o":[[0,0],[0,0],[0,0],[0,0],[0,0],[0,0],[0,0]],"v":[[52.367,-175.101],[52.367,-179.39],[58.778,-181.898],[52.367,-184.465],[52.367,-188.738],[65.069,-183.53],[65.069,-180.295]],"c":true},"ix":2},"nm":"Path 1","mn":"ADBE Vector Shape - Group","hd":false},{"ty":"fl","c":{"a":0,"k":[1,1,1,1],"ix":4},"o":{"a":0,"k":100,"ix":5},"r":1,"bm":0,"nm":"Fill 1","mn":"ADBE Vector Graphic - Fill","hd":false},{"ty":"tr","p":{"a":0,"k":[0,0],"ix":2},"a":{"a":0,"k":[0,0],"ix":1},"s":{"a":0,"k":[100,100],"ix":3},"r":{"a":0,"k":0,"ix":6},"o":{"a":0,"k":100,"ix":7},"sk":{"a":0,"k":0,"ix":4},"sa":{"a":0,"k":0,"ix":5},"nm":"Transform"}],"nm":"Group 1","np":2,"cix":2,"bm":0,"ix":1,"mn":"ADBE Vector Group","hd":false},{"ty":"gr","it":[{"ind":0,"ty":"sh","ix":1,"ks":{"a":0,"k":{"i":[[0,0],[0,0],[0,0],[0,0]],"o":[[0,0],[0,0],[0,0],[0,0]],"v":[[45.718,-191.871],[49.933,-191.871],[39.308,-169.123],[35.094,-169.123]],"c":true},"ix":2},"nm":"Path 1","mn":"ADBE Vector Shape - Group","hd":false},{"ty":"fl","c":{"a":0,"k":[1,1,1,1],"ix":4},"o":{"a":0,"k":100,"ix":5},"r":1,"bm":0,"nm":"Fill 1","mn":"ADBE Vector Graphic - Fill","hd":false},{"ty":"tr","p":{"a":0,"k":[0,0],"ix":2},"a":{"a":0,"k":[0,0],"ix":1},"s":{"a":0,"k":[100,100],"ix":3},"r":{"a":0,"k":0,"ix":6},"o":{"a":0,"k":100,"ix":7},"sk":{"a":0,"k":0,"ix":4},"sa":{"a":0,"k":0,"ix":5},"nm":"Transform"}],"nm":"Group 2","np":2,"cix":2,"bm":0,"ix":2,"mn":"ADBE Vector Group","hd":false},{"ty":"gr","it":[{"ind":0,"ty":"sh","ix":1,"ks":{"a":0,"k":{"i":[[0,0],[0,0],[0,0],[0,0],[0,0],[0,0],[0,0]],"o":[[0,0],[0,0],[0,0],[0,0],[0,0],[0,0],[0,0]],"v":[[20.645,-180.281],[20.645,-183.516],[33.347,-188.725],[33.347,-184.407],[26.936,-181.899],[33.347,-179.332],[33.347,-175.088]],"c":true},"ix":2},"nm":"Path 1","mn":"ADBE Vector Shape - Group","hd":false},{"ty":"fl","c":{"a":0,"k":[1,1,1,1],"ix":4},"o":{"a":0,"k":100,"ix":5},"r":1,"bm":0,"nm":"Fill 1","mn":"ADBE Vector Graphic - Fill","hd":false},{"ty":"tr","p":{"a":0,"k":[0,0],"ix":2},"a":{"a":0,"k":[0,0],"ix":1},"s":{"a":0,"k":[100,100],"ix":3},"r":{"a":0,"k":0,"ix":6},"o":{"a":0,"k":100,"ix":7},"sk":{"a":0,"k":0,"ix":4},"sa":{"a":0,"k":0,"ix":5},"nm":"Transform"}],"nm":"Group 3","np":2,"cix":2,"bm":0,"ix":3,"mn":"ADBE Vector Group","hd":false},{"ty":"gr","it":[{"ind":0,"ty":"sh","ix":1,"ks":{"a":0,"k":{"i":[[-4.793,0],[0,0],[0,4.793],[0,0],[4.793,0],[0,0],[0,-4.793],[0,0]],"o":[[0,0],[4.793,0],[0,0],[0,-4.793],[0,0],[-4.793,0],[0,0],[0.015,4.808]],"v":[[8.876,-154.966],[76.823,-154.966],[85.504,-163.647],[85.504,-201.308],[76.823,-209.988],[8.876,-209.988],[0.195,-201.308],[0.195,-163.647]],"c":true},"ix":2},"nm":"Path 1","mn":"ADBE Vector Shape - Group","hd":false},{"ty":"fl","c":{"a":0,"k":[0.482352942228,0.521568655968,0.988235294819,1],"ix":4},"o":{"a":0,"k":100,"ix":5},"r":1,"bm":0,"nm":"Fill 1","mn":"ADBE Vector Graphic - Fill","hd":false},{"ty":"tr","p":{"a":0,"k":[0,0],"ix":2},"a":{"a":0,"k":[0,0],"ix":1},"s":{"a":0,"k":[100,100],"ix":3},"r":{"a":0,"k":0,"ix":6},"o":{"a":0,"k":100,"ix":7},"sk":{"a":0,"k":0,"ix":4},"sa":{"a":0,"k":0,"ix":5},"nm":"Transform"}],"nm":"Group 4","np":2,"cix":2,"bm":0,"ix":4,"mn":"ADBE Vector Group","hd":false}],"ip":0,"op":1200,"st":0,"bm":0},{"ddd":0,"ind":10,"ty":4,"nm":"Layer 16","sr":1,"ks":{"o":{"a":0,"k":100,"ix":11},"r":{"a":0,"k":0,"ix":10},"p":{"a":0,"k":[573.831,243.362,0],"ix":2},"a":{"a":0,"k":[0,0,0],"ix":1},"s":{"a":0,"k":[100,100,100],"ix":6}},"ao":0,"shapes":[{"ty":"gr","it":[{"ind":0,"ty":"sh","ix":1,"ks":{"a":0,"k":{"i":[[0,0],[0,0],[0,0],[0,0],[0,0],[0,0],[0,0],[0,0],[0,0],[0,0],[0,0],[0,0],[0,0]],"o":[[0,0],[0,0],[0,0],[0,0],[0,0],[0,0],[0,0],[0,0],[0,0],[0,0],[0,0],[0,0],[0,0]],"v":[[-271.662,-119.785],[-199.061,-119.785],[-142.114,-119.785],[-142.114,-205.777],[-53.384,-207.109],[-53.384,-141.668],[177.068,-144.052],[178.305,-34.635],[271.662,-34.635],[271.662,20.276],[207.596,20.276],[207.596,207.109],[155.907,207.109]],"c":false},"ix":2},"nm":"Path 1","mn":"ADBE Vector Shape - Group","hd":false},{"ty":"st","c":{"a":0,"k":[0.721568627451,0.741176470588,1,1],"ix":3},"o":{"a":0,"k":100,"ix":4},"w":{"a":0,"k":2,"ix":5},"lc":1,"lj":1,"ml":4,"bm":0,"d":[{"n":"d","nm":"dash","v":{"a":0,"k":10,"ix":1}},{"n":"o","nm":"offset","v":{"a":1,"k":[{"i":{"x":[0.833],"y":[0.833]},"o":{"x":[0.167],"y":[0.167]},"t":0,"s":[0]},{"t":606,"s":[-515]}],"ix":7}}],"nm":"Stroke 1","mn":"ADBE Vector Graphic - Stroke","hd":false},{"ty":"tm","s":{"a":0,"k":0,"ix":1},"e":{"a":1,"k":[{"i":{"x":[0.667],"y":[1]},"o":{"x":[0.333],"y":[0]},"t":175,"s":[0]},{"t":261,"s":[100]}],"ix":2},"o":{"a":0,"k":0,"ix":3},"m":1,"ix":3,"nm":"Trim Paths 1","mn":"ADBE Vector Filter - Trim","hd":false},{"ty":"tr","p":{"a":0,"k":[0,0],"ix":2},"a":{"a":0,"k":[0,0],"ix":1},"s":{"a":0,"k":[100,100],"ix":3},"r":{"a":0,"k":0,"ix":6},"o":{"a":0,"k":100,"ix":7},"sk":{"a":0,"k":0,"ix":4},"sa":{"a":0,"k":0,"ix":5},"nm":"Transform"}],"nm":"Group 1","np":3,"cix":2,"bm":0,"ix":1,"mn":"ADBE Vector Group","hd":false}],"ip":0,"op":1200,"st":0,"bm":0},{"ddd":0,"ind":11,"ty":4,"nm":"Layer 11","sr":1,"ks":{"o":{"a":0,"k":100,"ix":11},"r":{"a":0,"k":0,"ix":10},"p":{"a":0,"k":[87.299,244.286,0],"ix":2},"a":{"a":0,"k":[0,0,0],"ix":1},"s":{"a":0,"k":[100,100,100],"ix":6}},"ao":0,"shapes":[{"ty":"gr","it":[{"ind":0,"ty":"sh","ix":1,"ks":{"a":0,"k":{"i":[[0,0],[0,0],[0,0],[0,0],[0,0]],"o":[[0,0],[0,0],[0,0],[0,0],[0,0]],"v":[[46.932,113.25],[-46.932,113.25],[-46.932,-40.514],[34.631,-40.514],[34.631,-113.25]],"c":false},"ix":2},"nm":"Path 1","mn":"ADBE Vector Shape - Group","hd":false},{"ty":"st","c":{"a":0,"k":[0.721568627451,0.741176470588,1,1],"ix":3},"o":{"a":0,"k":100,"ix":4},"w":{"a":0,"k":2,"ix":5},"lc":1,"lj":1,"ml":4,"bm":0,"d":[{"n":"d","nm":"dash","v":{"a":0,"k":10,"ix":1}},{"n":"o","nm":"offset","v":{"a":1,"k":[{"i":{"x":[0.833],"y":[0.833]},"o":{"x":[0.167],"y":[0.167]},"t":0,"s":[0]},{"t":601,"s":[-516]}],"ix":7}}],"nm":"Stroke 1","mn":"ADBE Vector Graphic - Stroke","hd":false},{"ty":"tm","s":{"a":0,"k":0,"ix":1},"e":{"a":1,"k":[{"i":{"x":[0.833],"y":[0.833]},"o":{"x":[0.167],"y":[0.167]},"t":114,"s":[0]},{"t":170,"s":[100]}],"ix":2},"o":{"a":0,"k":0,"ix":3},"m":1,"ix":3,"nm":"Trim Paths 1","mn":"ADBE Vector Filter - Trim","hd":false},{"ty":"tr","p":{"a":0,"k":[0,0],"ix":2},"a":{"a":0,"k":[0,0],"ix":1},"s":{"a":0,"k":[100,100],"ix":3},"r":{"a":0,"k":0,"ix":6},"o":{"a":0,"k":100,"ix":7},"sk":{"a":0,"k":0,"ix":4},"sa":{"a":0,"k":0,"ix":5},"nm":"Transform"}],"nm":"Group 1","np":3,"cix":2,"bm":0,"ix":1,"mn":"ADBE Vector Group","hd":false}],"ip":0,"op":1200,"st":0,"bm":0},{"ddd":0,"ind":12,"ty":4,"nm":"Layer 10","sr":1,"ks":{"o":{"a":0,"k":100,"ix":11},"r":{"a":0,"k":0,"ix":10},"p":{"a":0,"k":[244.214,266.979,0],"ix":2},"a":{"a":0,"k":[-237.786,60.979,0],"ix":1},"s":{"a":0,"k":[100,100,100],"ix":6}},"ao":0,"shapes":[{"ty":"gr","it":[{"ind":0,"ty":"sh","ix":1,"ks":{"a":1,"k":[{"i":{"x":0.667,"y":1},"o":{"x":0.333,"y":0},"t":185,"s":[{"i":[[0,0],[0,0],[0,0],[0,0]],"o":[[0,0],[0,0],[0,0],[0,0]],"v":[[-297.318,70.801],[-297.379,70.801],[-297.379,78],[-297.318,78]],"c":true}]},{"t":218,"s":[{"i":[[0,0],[0,0],[0,0],[0,0]],"o":[[0,0],[0,0],[0,0],[0,0]],"v":[[-178.193,70.801],[-297.379,70.801],[-297.379,78],[-178.193,78]],"c":true}]}],"ix":2},"nm":"Path 1","mn":"ADBE Vector Shape - Group","hd":false},{"ty":"fl","c":{"a":0,"k":[1,1,1,1],"ix":4},"o":{"a":0,"k":100,"ix":5},"r":1,"bm":0,"nm":"Fill 1","mn":"ADBE Vector Graphic - Fill","hd":false},{"ty":"tr","p":{"a":0,"k":[0,0],"ix":2},"a":{"a":0,"k":[0,0],"ix":1},"s":{"a":0,"k":[100,100],"ix":3},"r":{"a":0,"k":0,"ix":6},"o":{"a":0,"k":100,"ix":7},"sk":{"a":0,"k":0,"ix":4},"sa":{"a":0,"k":0,"ix":5},"nm":"Transform"}],"nm":"Group 1","np":2,"cix":2,"bm":0,"ix":1,"mn":"ADBE Vector Group","hd":false},{"ty":"gr","it":[{"ind":0,"ty":"sh","ix":1,"ks":{"a":1,"k":[{"i":{"x":0.667,"y":1},"o":{"x":0.333,"y":0},"t":185,"s":[{"i":[[0,0],[0,0],[0,0],[0,0]],"o":[[0,0],[0,0],[0,0],[0,0]],"v":[[-297.318,57.215],[-297.379,57.215],[-297.379,64.414],[-297.318,64.414]],"c":true}]},{"t":212,"s":[{"i":[[0,0],[0,0],[0,0],[0,0]],"o":[[0,0],[0,0],[0,0],[0,0]],"v":[[-178.193,57.215],[-297.379,57.215],[-297.379,64.414],[-178.193,64.414]],"c":true}]}],"ix":2},"nm":"Path 1","mn":"ADBE Vector Shape - Group","hd":false},{"ty":"fl","c":{"a":0,"k":[1,1,1,1],"ix":4},"o":{"a":0,"k":100,"ix":5},"r":1,"bm":0,"nm":"Fill 1","mn":"ADBE Vector Graphic - Fill","hd":false},{"ty":"tr","p":{"a":0,"k":[0,0],"ix":2},"a":{"a":0,"k":[0,0],"ix":1},"s":{"a":0,"k":[100,100],"ix":3},"r":{"a":0,"k":0,"ix":6},"o":{"a":0,"k":100,"ix":7},"sk":{"a":0,"k":0,"ix":4},"sa":{"a":0,"k":0,"ix":5},"nm":"Transform"}],"nm":"Group 2","np":2,"cix":2,"bm":0,"ix":2,"mn":"ADBE Vector Group","hd":false},{"ty":"gr","it":[{"ind":0,"ty":"sh","ix":1,"ks":{"a":1,"k":[{"i":{"x":0.667,"y":1},"o":{"x":0.333,"y":0},"t":185,"s":[{"i":[[0,0],[0,0],[0,0],[0,0]],"o":[[0,0],[0,0],[0,0],[0,0]],"v":[[-297.318,43.957],[-297.379,43.957],[-297.379,50.827],[-297.318,50.827]],"c":true}]},{"t":205,"s":[{"i":[[0,0],[0,0],[0,0],[0,0]],"o":[[0,0],[0,0],[0,0],[0,0]],"v":[[-178.193,43.957],[-297.379,43.957],[-297.379,50.827],[-178.193,50.827]],"c":true}]}],"ix":2},"nm":"Path 1","mn":"ADBE Vector Shape - Group","hd":false},{"ty":"fl","c":{"a":0,"k":[1,1,1,1],"ix":4},"o":{"a":0,"k":100,"ix":5},"r":1,"bm":0,"nm":"Fill 1","mn":"ADBE Vector Graphic - Fill","hd":false},{"ty":"tr","p":{"a":0,"k":[0,0],"ix":2},"a":{"a":0,"k":[0,0],"ix":1},"s":{"a":0,"k":[100,100],"ix":3},"r":{"a":0,"k":0,"ix":6},"o":{"a":0,"k":100,"ix":7},"sk":{"a":0,"k":0,"ix":4},"sa":{"a":0,"k":0,"ix":5},"nm":"Transform"}],"nm":"Group 3","np":2,"cix":2,"bm":0,"ix":3,"mn":"ADBE Vector Group","hd":false}],"ip":50,"op":1250,"st":50,"bm":0},{"ddd":0,"ind":13,"ty":4,"nm":"Merged Shape Layer 2","sr":1,"ks":{"o":{"a":0,"k":100,"ix":11},"r":{"a":0,"k":0,"ix":10},"p":{"a":0,"k":[151.462,266.316,0],"ix":2},"a":{"a":0,"k":[312.212,423.316,0],"ix":1},"s":{"a":1,"k":[{"i":{"x":[0.042,0.042,0.667],"y":[1,1,1]},"o":{"x":[0.121,0.121,0.333],"y":[0,0,0]},"t":153,"s":[0,0,100]},{"t":178,"s":[100,100,100]}],"ix":6}},"ao":0,"shapes":[{"ty":"gr","it":[{"ty":"gr","it":[{"ind":0,"ty":"sh","ix":1,"ks":{"a":0,"k":{"i":[[-1.859,0],[0,0],[-1.314,-1.314],[0,-1.859],[0,0],[0,0],[0,0],[-1.314,1.314]],"o":[[0,0],[1.859,0],[1.315,1.314],[0,0],[0,0],[0,0],[0,-1.859],[1.315,-1.314]],"v":[[-1.355,-6.086],[1.354,-6.086],[6.311,-4.033],[8.363,0.923],[8.363,6.086],[-8.364,6.086],[-8.364,0.923],[-6.312,-4.033]],"c":true},"ix":2},"nm":"Path 1","mn":"ADBE Vector Shape - Group","hd":false},{"ty":"fl","c":{"a":0,"k":[0.800000011921,0.815686285496,1,1],"ix":4},"o":{"a":0,"k":100,"ix":5},"r":1,"bm":0,"nm":"Fill 1","mn":"ADBE Vector Graphic - Fill","hd":false},{"ty":"tr","p":{"a":0,"k":[0,0],"ix":2},"a":{"a":0,"k":[0,0],"ix":1},"s":{"a":0,"k":[100,100],"ix":3},"r":{"a":0,"k":0,"ix":6},"o":{"a":0,"k":100,"ix":7},"sk":{"a":0,"k":0,"ix":4},"sa":{"a":0,"k":0,"ix":5},"nm":"Transform"}],"nm":"Group 1","np":2,"cix":2,"bm":0,"ix":1,"mn":"ADBE Vector Group","hd":false},{"ty":"tr","p":{"a":0,"k":[312.216,427.369],"ix":2},"a":{"a":0,"k":[0,0],"ix":1},"s":{"a":0,"k":[100,100],"ix":3},"r":{"a":0,"k":0,"ix":6},"o":{"a":0,"k":100,"ix":7},"sk":{"a":0,"k":0,"ix":4},"sa":{"a":0,"k":0,"ix":5},"nm":"Transform"}],"nm":"Layer 10","np":1,"cix":2,"bm":0,"ix":1,"mn":"ADBE Vector Group","hd":false},{"ty":"gr","it":[{"ty":"gr","it":[{"ind":0,"ty":"sh","ix":1,"ks":{"a":0,"k":{"i":[[0.003,-0.554],[0.465,-0.689],[0.769,-0.314],[0.814,0.165],[0.586,0.589],[0.16,0.816],[-0.319,0.767],[-0.691,0.462],[-0.831,0],[-0.511,-0.213],[-0.391,-0.393],[-0.21,-0.513]],"o":[[-0.005,0.831],[-0.465,0.688],[-0.769,0.315],[-0.814,-0.165],[-0.586,-0.589],[-0.161,-0.815],[0.319,-0.767],[0.691,-0.461],[0.554,0],[0.512,0.213],[0.39,0.393],[0.209,0.512]],"v":[[4.205,0.024],[3.485,2.354],[1.593,3.892],[-0.835,4.122],[-2.982,2.966],[-4.126,0.812],[-3.883,-1.614],[-2.334,-3.498],[0,-4.205],[1.614,-3.882],[2.982,-2.965],[3.892,-1.592]],"c":true},"ix":2},"nm":"Path 1","mn":"ADBE Vector Shape - Group","hd":false},{"ty":"fl","c":{"a":0,"k":[0.800000011921,0.815686285496,1,1],"ix":4},"o":{"a":0,"k":100,"ix":5},"r":1,"bm":0,"nm":"Fill 1","mn":"ADBE Vector Graphic - Fill","hd":false},{"ty":"tr","p":{"a":0,"k":[0,0],"ix":2},"a":{"a":0,"k":[0,0],"ix":1},"s":{"a":0,"k":[100,100],"ix":3},"r":{"a":0,"k":0,"ix":6},"o":{"a":0,"k":100,"ix":7},"sk":{"a":0,"k":0,"ix":4},"sa":{"a":0,"k":0,"ix":5},"nm":"Transform"}],"nm":"Group 1","np":2,"cix":2,"bm":0,"ix":1,"mn":"ADBE Vector Group","hd":false},{"ty":"tr","p":{"a":0,"k":[312.225,416.773],"ix":2},"a":{"a":0,"k":[0,0],"ix":1},"s":{"a":0,"k":[100,100],"ix":3},"r":{"a":0,"k":0,"ix":6},"o":{"a":0,"k":100,"ix":7},"sk":{"a":0,"k":0,"ix":4},"sa":{"a":0,"k":0,"ix":5},"nm":"Transform"}],"nm":"Layer 9","np":1,"cix":2,"bm":0,"ix":2,"mn":"ADBE Vector Group","hd":false},{"ty":"gr","it":[{"ty":"gr","it":[{"ind":0,"ty":"sh","ix":1,"ks":{"a":0,"k":{"i":[[0,-4.681],[1.94,-2.902],[3.226,-1.336],[3.424,0.681],[2.468,2.468],[0.681,3.424],[-1.336,3.226],[-2.903,1.94],[-3.491,0],[-3.309,-3.31]],"o":[[0,3.49],[-1.939,2.903],[-3.225,1.336],[-3.424,-0.681],[-2.468,-2.468],[-0.681,-3.424],[1.336,-3.225],[2.902,-1.939],[4.681,0],[3.31,3.31]],"v":[[17.65,0],[14.675,9.805],[6.754,16.306],[-3.443,17.31],[-12.48,12.48],[-17.311,3.443],[-16.306,-6.755],[-9.805,-14.676],[0,-17.65],[12.48,-12.481]],"c":true},"ix":2},"nm":"Path 1","mn":"ADBE Vector Shape - Group","hd":false},{"ty":"fl","c":{"a":0,"k":[1,1,1,1],"ix":4},"o":{"a":0,"k":100,"ix":5},"r":1,"bm":0,"nm":"Fill 1","mn":"ADBE Vector Graphic - Fill","hd":false},{"ty":"tr","p":{"a":0,"k":[0,0],"ix":2},"a":{"a":0,"k":[0,0],"ix":1},"s":{"a":0,"k":[100,100],"ix":3},"r":{"a":0,"k":0,"ix":6},"o":{"a":0,"k":100,"ix":7},"sk":{"a":0,"k":0,"ix":4},"sa":{"a":0,"k":0,"ix":5},"nm":"Transform"}],"nm":"Group 1","np":2,"cix":2,"bm":0,"ix":1,"mn":"ADBE Vector Group","hd":false},{"ty":"tr","p":{"a":0,"k":[312.212,423.316],"ix":2},"a":{"a":0,"k":[0,0],"ix":1},"s":{"a":0,"k":[100,100],"ix":3},"r":{"a":0,"k":0,"ix":6},"o":{"a":0,"k":100,"ix":7},"sk":{"a":0,"k":0,"ix":4},"sa":{"a":0,"k":0,"ix":5},"nm":"Transform"}],"nm":"Layer 8","np":1,"cix":2,"bm":0,"ix":3,"mn":"ADBE Vector Group","hd":false}],"ip":50,"op":1250,"st":50,"bm":0},{"ddd":0,"ind":14,"ty":4,"nm":"Layer 9","sr":1,"ks":{"o":{"a":0,"k":100,"ix":11},"r":{"a":0,"k":0,"ix":10},"p":{"a":0,"k":[220.695,266.386,0],"ix":2},"a":{"a":0,"k":[0,0,0],"ix":1},"s":{"a":0,"k":[100,100,100],"ix":6}},"ao":0,"shapes":[{"ty":"gr","it":[{"ind":0,"ty":"sh","ix":1,"ks":{"a":1,"k":[{"i":{"x":0.059,"y":1},"o":{"x":0.189,"y":0},"t":110,"s":[{"i":[[0,0],[0,0],[0,0],[0,0]],"o":[[0,0],[0,0],[0,0],[0,0]],"v":[[100.222,-25.847],[100.215,-25.801],[100.215,25.893],[100.222,25.847]],"c":true}]},{"t":154,"s":[{"i":[[0,0],[0,0],[0,0],[0,0]],"o":[[0,0],[0,0],[0,0],[0,0]],"v":[[100.222,-25.847],[-100.222,-25.847],[-100.222,25.847],[100.222,25.847]],"c":true}]}],"ix":2},"nm":"Path 1","mn":"ADBE Vector Shape - Group","hd":false},{"ty":"fl","c":{"a":0,"k":[0.686274528503,0.713725507259,1,1],"ix":4},"o":{"a":0,"k":100,"ix":5},"r":1,"bm":0,"nm":"Fill 1","mn":"ADBE Vector Graphic - Fill","hd":false},{"ty":"tr","p":{"a":0,"k":[0,0],"ix":2},"a":{"a":0,"k":[0,0],"ix":1},"s":{"a":0,"k":[100,100],"ix":3},"r":{"a":0,"k":0,"ix":6},"o":{"a":0,"k":100,"ix":7},"sk":{"a":0,"k":0,"ix":4},"sa":{"a":0,"k":0,"ix":5},"nm":"Transform"}],"nm":"Group 1","np":2,"cix":2,"bm":0,"ix":1,"mn":"ADBE Vector Group","hd":false}],"ip":110,"op":1250,"st":50,"bm":0},{"ddd":0,"ind":15,"ty":4,"nm":"Layer 8","sr":1,"ks":{"o":{"a":0,"k":100,"ix":11},"r":{"a":0,"k":0,"ix":10},"p":{"a":0,"k":[482,286,0],"ix":2},"a":{"a":0,"k":[0,0,0],"ix":1},"s":{"a":0,"k":[100,100,100],"ix":6}},"ao":0,"shapes":[{"ty":"gr","it":[{"ind":0,"ty":"sh","ix":1,"ks":{"a":1,"k":[{"i":{"x":0.667,"y":1},"o":{"x":0.333,"y":0},"t":135,"s":[{"i":[[0,0],[0,0],[0,0],[0,0]],"o":[[0,0],[0,0],[0,0],[0,0]],"v":[[-297.318,70.801],[-297.379,70.801],[-297.379,78],[-297.318,78]],"c":true}]},{"t":168,"s":[{"i":[[0,0],[0,0],[0,0],[0,0]],"o":[[0,0],[0,0],[0,0],[0,0]],"v":[[-178.193,70.801],[-297.379,70.801],[-297.379,78],[-178.193,78]],"c":true}]}],"ix":2},"nm":"Path 1","mn":"ADBE Vector Shape - Group","hd":false},{"ty":"fl","c":{"a":0,"k":[1,1,1,1],"ix":4},"o":{"a":0,"k":100,"ix":5},"r":1,"bm":0,"nm":"Fill 1","mn":"ADBE Vector Graphic - Fill","hd":false},{"ty":"tr","p":{"a":0,"k":[0,0],"ix":2},"a":{"a":0,"k":[0,0],"ix":1},"s":{"a":0,"k":[100,100],"ix":3},"r":{"a":0,"k":0,"ix":6},"o":{"a":0,"k":100,"ix":7},"sk":{"a":0,"k":0,"ix":4},"sa":{"a":0,"k":0,"ix":5},"nm":"Transform"}],"nm":"Group 1","np":2,"cix":2,"bm":0,"ix":1,"mn":"ADBE Vector Group","hd":false},{"ty":"gr","it":[{"ind":0,"ty":"sh","ix":1,"ks":{"a":1,"k":[{"i":{"x":0.667,"y":1},"o":{"x":0.333,"y":0},"t":135,"s":[{"i":[[0,0],[0,0],[0,0],[0,0]],"o":[[0,0],[0,0],[0,0],[0,0]],"v":[[-297.318,57.215],[-297.379,57.215],[-297.379,64.414],[-297.318,64.414]],"c":true}]},{"t":162,"s":[{"i":[[0,0],[0,0],[0,0],[0,0]],"o":[[0,0],[0,0],[0,0],[0,0]],"v":[[-178.193,57.215],[-297.379,57.215],[-297.379,64.414],[-178.193,64.414]],"c":true}]}],"ix":2},"nm":"Path 1","mn":"ADBE Vector Shape - Group","hd":false},{"ty":"fl","c":{"a":0,"k":[1,1,1,1],"ix":4},"o":{"a":0,"k":100,"ix":5},"r":1,"bm":0,"nm":"Fill 1","mn":"ADBE Vector Graphic - Fill","hd":false},{"ty":"tr","p":{"a":0,"k":[0,0],"ix":2},"a":{"a":0,"k":[0,0],"ix":1},"s":{"a":0,"k":[100,100],"ix":3},"r":{"a":0,"k":0,"ix":6},"o":{"a":0,"k":100,"ix":7},"sk":{"a":0,"k":0,"ix":4},"sa":{"a":0,"k":0,"ix":5},"nm":"Transform"}],"nm":"Group 2","np":2,"cix":2,"bm":0,"ix":2,"mn":"ADBE Vector Group","hd":false},{"ty":"gr","it":[{"ind":0,"ty":"sh","ix":1,"ks":{"a":1,"k":[{"i":{"x":0.667,"y":1},"o":{"x":0.333,"y":0},"t":135,"s":[{"i":[[0,0],[0,0],[0,0],[0,0]],"o":[[0,0],[0,0],[0,0],[0,0]],"v":[[-297.318,43.957],[-297.379,43.957],[-297.379,50.827],[-297.318,50.827]],"c":true}]},{"t":155,"s":[{"i":[[0,0],[0,0],[0,0],[0,0]],"o":[[0,0],[0,0],[0,0],[0,0]],"v":[[-178.193,43.957],[-297.379,43.957],[-297.379,50.827],[-178.193,50.827]],"c":true}]}],"ix":2},"nm":"Path 1","mn":"ADBE Vector Shape - Group","hd":false},{"ty":"fl","c":{"a":0,"k":[1,1,1,1],"ix":4},"o":{"a":0,"k":100,"ix":5},"r":1,"bm":0,"nm":"Fill 1","mn":"ADBE Vector Graphic - Fill","hd":false},{"ty":"tr","p":{"a":0,"k":[0,0],"ix":2},"a":{"a":0,"k":[0,0],"ix":1},"s":{"a":0,"k":[100,100],"ix":3},"r":{"a":0,"k":0,"ix":6},"o":{"a":0,"k":100,"ix":7},"sk":{"a":0,"k":0,"ix":4},"sa":{"a":0,"k":0,"ix":5},"nm":"Transform"}],"nm":"Group 3","np":2,"cix":2,"bm":0,"ix":3,"mn":"ADBE Vector Group","hd":false}],"ip":0,"op":1200,"st":0,"bm":0},{"ddd":0,"ind":16,"ty":4,"nm":"Merged Shape Layer","sr":1,"ks":{"o":{"a":0,"k":100,"ix":11},"r":{"a":0,"k":0,"ix":10},"p":{"a":0,"k":[151.462,346.316,0],"ix":2},"a":{"a":0,"k":[312.212,423.316,0],"ix":1},"s":{"a":1,"k":[{"i":{"x":[0.042,0.042,0.667],"y":[1,1,1]},"o":{"x":[0.121,0.121,0.333],"y":[0,0,0]},"t":103,"s":[0,0,100]},{"t":128,"s":[100,100,100]}],"ix":6}},"ao":0,"shapes":[{"ty":"gr","it":[{"ty":"gr","it":[{"ind":0,"ty":"sh","ix":1,"ks":{"a":0,"k":{"i":[[-1.859,0],[0,0],[-1.314,-1.314],[0,-1.859],[0,0],[0,0],[0,0],[-1.314,1.314]],"o":[[0,0],[1.859,0],[1.315,1.314],[0,0],[0,0],[0,0],[0,-1.859],[1.315,-1.314]],"v":[[-1.355,-6.086],[1.354,-6.086],[6.311,-4.033],[8.363,0.923],[8.363,6.086],[-8.364,6.086],[-8.364,0.923],[-6.312,-4.033]],"c":true},"ix":2},"nm":"Path 1","mn":"ADBE Vector Shape - Group","hd":false},{"ty":"fl","c":{"a":0,"k":[0.800000011921,0.815686285496,1,1],"ix":4},"o":{"a":0,"k":100,"ix":5},"r":1,"bm":0,"nm":"Fill 1","mn":"ADBE Vector Graphic - Fill","hd":false},{"ty":"tr","p":{"a":0,"k":[0,0],"ix":2},"a":{"a":0,"k":[0,0],"ix":1},"s":{"a":0,"k":[100,100],"ix":3},"r":{"a":0,"k":0,"ix":6},"o":{"a":0,"k":100,"ix":7},"sk":{"a":0,"k":0,"ix":4},"sa":{"a":0,"k":0,"ix":5},"nm":"Transform"}],"nm":"Group 1","np":2,"cix":2,"bm":0,"ix":1,"mn":"ADBE Vector Group","hd":false},{"ty":"tr","p":{"a":0,"k":[312.216,427.369],"ix":2},"a":{"a":0,"k":[0,0],"ix":1},"s":{"a":0,"k":[100,100],"ix":3},"r":{"a":0,"k":0,"ix":6},"o":{"a":0,"k":100,"ix":7},"sk":{"a":0,"k":0,"ix":4},"sa":{"a":0,"k":0,"ix":5},"nm":"Transform"}],"nm":"Layer 10","np":1,"cix":2,"bm":0,"ix":1,"mn":"ADBE Vector Group","hd":false},{"ty":"gr","it":[{"ty":"gr","it":[{"ind":0,"ty":"sh","ix":1,"ks":{"a":0,"k":{"i":[[0.003,-0.554],[0.465,-0.689],[0.769,-0.314],[0.814,0.165],[0.586,0.589],[0.16,0.816],[-0.319,0.767],[-0.691,0.462],[-0.831,0],[-0.511,-0.213],[-0.391,-0.393],[-0.21,-0.513]],"o":[[-0.005,0.831],[-0.465,0.688],[-0.769,0.315],[-0.814,-0.165],[-0.586,-0.589],[-0.161,-0.815],[0.319,-0.767],[0.691,-0.461],[0.554,0],[0.512,0.213],[0.39,0.393],[0.209,0.512]],"v":[[4.205,0.024],[3.485,2.354],[1.593,3.892],[-0.835,4.122],[-2.982,2.966],[-4.126,0.812],[-3.883,-1.614],[-2.334,-3.498],[0,-4.205],[1.614,-3.882],[2.982,-2.965],[3.892,-1.592]],"c":true},"ix":2},"nm":"Path 1","mn":"ADBE Vector Shape - Group","hd":false},{"ty":"fl","c":{"a":0,"k":[0.800000011921,0.815686285496,1,1],"ix":4},"o":{"a":0,"k":100,"ix":5},"r":1,"bm":0,"nm":"Fill 1","mn":"ADBE Vector Graphic - Fill","hd":false},{"ty":"tr","p":{"a":0,"k":[0,0],"ix":2},"a":{"a":0,"k":[0,0],"ix":1},"s":{"a":0,"k":[100,100],"ix":3},"r":{"a":0,"k":0,"ix":6},"o":{"a":0,"k":100,"ix":7},"sk":{"a":0,"k":0,"ix":4},"sa":{"a":0,"k":0,"ix":5},"nm":"Transform"}],"nm":"Group 1","np":2,"cix":2,"bm":0,"ix":1,"mn":"ADBE Vector Group","hd":false},{"ty":"tr","p":{"a":0,"k":[312.225,416.773],"ix":2},"a":{"a":0,"k":[0,0],"ix":1},"s":{"a":0,"k":[100,100],"ix":3},"r":{"a":0,"k":0,"ix":6},"o":{"a":0,"k":100,"ix":7},"sk":{"a":0,"k":0,"ix":4},"sa":{"a":0,"k":0,"ix":5},"nm":"Transform"}],"nm":"Layer 9","np":1,"cix":2,"bm":0,"ix":2,"mn":"ADBE Vector Group","hd":false},{"ty":"gr","it":[{"ty":"gr","it":[{"ind":0,"ty":"sh","ix":1,"ks":{"a":0,"k":{"i":[[0,-4.681],[1.94,-2.902],[3.226,-1.336],[3.424,0.681],[2.468,2.468],[0.681,3.424],[-1.336,3.226],[-2.903,1.94],[-3.491,0],[-3.309,-3.31]],"o":[[0,3.49],[-1.939,2.903],[-3.225,1.336],[-3.424,-0.681],[-2.468,-2.468],[-0.681,-3.424],[1.336,-3.225],[2.902,-1.939],[4.681,0],[3.31,3.31]],"v":[[17.65,0],[14.675,9.805],[6.754,16.306],[-3.443,17.31],[-12.48,12.48],[-17.311,3.443],[-16.306,-6.755],[-9.805,-14.676],[0,-17.65],[12.48,-12.481]],"c":true},"ix":2},"nm":"Path 1","mn":"ADBE Vector Shape - Group","hd":false},{"ty":"fl","c":{"a":0,"k":[1,1,1,1],"ix":4},"o":{"a":0,"k":100,"ix":5},"r":1,"bm":0,"nm":"Fill 1","mn":"ADBE Vector Graphic - Fill","hd":false},{"ty":"tr","p":{"a":0,"k":[0,0],"ix":2},"a":{"a":0,"k":[0,0],"ix":1},"s":{"a":0,"k":[100,100],"ix":3},"r":{"a":0,"k":0,"ix":6},"o":{"a":0,"k":100,"ix":7},"sk":{"a":0,"k":0,"ix":4},"sa":{"a":0,"k":0,"ix":5},"nm":"Transform"}],"nm":"Group 1","np":2,"cix":2,"bm":0,"ix":1,"mn":"ADBE Vector Group","hd":false},{"ty":"tr","p":{"a":0,"k":[312.212,423.316],"ix":2},"a":{"a":0,"k":[0,0],"ix":1},"s":{"a":0,"k":[100,100],"ix":3},"r":{"a":0,"k":0,"ix":6},"o":{"a":0,"k":100,"ix":7},"sk":{"a":0,"k":0,"ix":4},"sa":{"a":0,"k":0,"ix":5},"nm":"Transform"}],"nm":"Layer 8","np":1,"cix":2,"bm":0,"ix":3,"mn":"ADBE Vector Group","hd":false}],"ip":0,"op":1200,"st":0,"bm":0},{"ddd":0,"ind":17,"ty":4,"nm":"Layer 7","sr":1,"ks":{"o":{"a":0,"k":100,"ix":11},"r":{"a":0,"k":0,"ix":10},"p":{"a":0,"k":[220.695,346.386,0],"ix":2},"a":{"a":0,"k":[0,0,0],"ix":1},"s":{"a":0,"k":[100,100,100],"ix":6}},"ao":0,"shapes":[{"ty":"gr","it":[{"ind":0,"ty":"sh","ix":1,"ks":{"a":1,"k":[{"i":{"x":0.059,"y":1},"o":{"x":0.189,"y":0},"t":60,"s":[{"i":[[0,0],[0,0],[0,0],[0,0]],"o":[[0,0],[0,0],[0,0],[0,0]],"v":[[100.222,-25.847],[100.215,-25.801],[100.215,25.893],[100.222,25.847]],"c":true}]},{"t":104,"s":[{"i":[[0,0],[0,0],[0,0],[0,0]],"o":[[0,0],[0,0],[0,0],[0,0]],"v":[[100.222,-25.847],[-100.222,-25.847],[-100.222,25.847],[100.222,25.847]],"c":true}]}],"ix":2},"nm":"Path 1","mn":"ADBE Vector Shape - Group","hd":false},{"ty":"fl","c":{"a":0,"k":[0.686274528503,0.713725507259,1,1],"ix":4},"o":{"a":0,"k":100,"ix":5},"r":1,"bm":0,"nm":"Fill 1","mn":"ADBE Vector Graphic - Fill","hd":false},{"ty":"tr","p":{"a":0,"k":[0,0],"ix":2},"a":{"a":0,"k":[0,0],"ix":1},"s":{"a":0,"k":[100,100],"ix":3},"r":{"a":0,"k":0,"ix":6},"o":{"a":0,"k":100,"ix":7},"sk":{"a":0,"k":0,"ix":4},"sa":{"a":0,"k":0,"ix":5},"nm":"Transform"}],"nm":"Group 1","np":2,"cix":2,"bm":0,"ix":1,"mn":"ADBE Vector Group","hd":false}],"ip":60,"op":1200,"st":0,"bm":0},{"ddd":0,"ind":18,"ty":4,"nm":"Layer 5","sr":1,"ks":{"o":{"a":0,"k":100,"ix":11},"r":{"a":0,"k":0,"ix":10},"p":{"a":0,"k":[431.192,237.155,0],"ix":2},"a":{"a":0,"k":[0,0,0],"ix":1},"s":{"a":0,"k":[100,100,100],"ix":6}},"ao":0,"shapes":[{"ty":"gr","it":[{"ind":0,"ty":"sh","ix":1,"ks":{"a":1,"k":[{"i":{"x":0.667,"y":1},"o":{"x":0.333,"y":0},"t":59,"s":[{"i":[[0,0],[0,0],[0,0],[0,0]],"o":[[0,0],[0,0],[0,0],[0,0]],"v":[[-54.886,-4.908],[-54.926,-4.923],[-54.926,4.923],[-54.886,4.939]],"c":true}]},{"t":73,"s":[{"i":[[0,0],[0,0],[0,0],[0,0]],"o":[[0,0],[0,0],[0,0],[0,0]],"v":[[54.926,-4.923],[-54.926,-4.923],[-54.926,4.923],[54.926,4.923]],"c":true}]}],"ix":2},"nm":"Path 1","mn":"ADBE Vector Shape - Group","hd":false},{"ty":"fl","c":{"a":0,"k":[1,1,1,1],"ix":4},"o":{"a":0,"k":100,"ix":5},"r":1,"bm":0,"nm":"Fill 1","mn":"ADBE Vector Graphic - Fill","hd":false},{"ty":"tr","p":{"a":0,"k":[0,120],"ix":2},"a":{"a":0,"k":[0,0],"ix":1},"s":{"a":0,"k":[100,100],"ix":3},"r":{"a":0,"k":0,"ix":6},"o":{"a":0,"k":100,"ix":7},"sk":{"a":0,"k":0,"ix":4},"sa":{"a":0,"k":0,"ix":5},"nm":"Transform"}],"nm":"Group 7","np":2,"cix":2,"bm":0,"ix":1,"mn":"ADBE Vector Group","hd":false},{"ty":"gr","it":[{"ind":0,"ty":"sh","ix":1,"ks":{"a":1,"k":[{"i":{"x":0.667,"y":1},"o":{"x":0.333,"y":0},"t":57,"s":[{"i":[[0,0],[0,0],[0,0],[0,0]],"o":[[0,0],[0,0],[0,0],[0,0]],"v":[[-54.886,-4.908],[-54.926,-4.923],[-54.926,4.923],[-54.886,4.939]],"c":true}]},{"t":71,"s":[{"i":[[0,0],[0,0],[0,0],[0,0]],"o":[[0,0],[0,0],[0,0],[0,0]],"v":[[54.926,-4.923],[-54.926,-4.923],[-54.926,4.923],[54.926,4.923]],"c":true}]}],"ix":2},"nm":"Path 1","mn":"ADBE Vector Shape - Group","hd":false},{"ty":"fl","c":{"a":0,"k":[1,1,1,1],"ix":4},"o":{"a":0,"k":100,"ix":5},"r":1,"bm":0,"nm":"Fill 1","mn":"ADBE Vector Graphic - Fill","hd":false},{"ty":"tr","p":{"a":0,"k":[0,100],"ix":2},"a":{"a":0,"k":[0,0],"ix":1},"s":{"a":0,"k":[100,100],"ix":3},"r":{"a":0,"k":0,"ix":6},"o":{"a":0,"k":100,"ix":7},"sk":{"a":0,"k":0,"ix":4},"sa":{"a":0,"k":0,"ix":5},"nm":"Transform"}],"nm":"Group 6","np":2,"cix":2,"bm":0,"ix":2,"mn":"ADBE Vector Group","hd":false},{"ty":"gr","it":[{"ind":0,"ty":"sh","ix":1,"ks":{"a":1,"k":[{"i":{"x":0.667,"y":1},"o":{"x":0.333,"y":0},"t":55,"s":[{"i":[[0,0],[0,0],[0,0],[0,0]],"o":[[0,0],[0,0],[0,0],[0,0]],"v":[[-54.886,-4.908],[-54.926,-4.923],[-54.926,4.923],[-54.886,4.939]],"c":true}]},{"t":69,"s":[{"i":[[0,0],[0,0],[0,0],[0,0]],"o":[[0,0],[0,0],[0,0],[0,0]],"v":[[54.926,-4.923],[-54.926,-4.923],[-54.926,4.923],[54.926,4.923]],"c":true}]}],"ix":2},"nm":"Path 1","mn":"ADBE Vector Shape - Group","hd":false},{"ty":"fl","c":{"a":0,"k":[1,1,1,1],"ix":4},"o":{"a":0,"k":100,"ix":5},"r":1,"bm":0,"nm":"Fill 1","mn":"ADBE Vector Graphic - Fill","hd":false},{"ty":"tr","p":{"a":0,"k":[0,80],"ix":2},"a":{"a":0,"k":[0,0],"ix":1},"s":{"a":0,"k":[100,100],"ix":3},"r":{"a":0,"k":0,"ix":6},"o":{"a":0,"k":100,"ix":7},"sk":{"a":0,"k":0,"ix":4},"sa":{"a":0,"k":0,"ix":5},"nm":"Transform"}],"nm":"Group 5","np":2,"cix":2,"bm":0,"ix":3,"mn":"ADBE Vector Group","hd":false},{"ty":"gr","it":[{"ind":0,"ty":"sh","ix":1,"ks":{"a":1,"k":[{"i":{"x":0.667,"y":1},"o":{"x":0.333,"y":0},"t":53,"s":[{"i":[[0,0],[0,0],[0,0],[0,0]],"o":[[0,0],[0,0],[0,0],[0,0]],"v":[[-54.886,-4.908],[-54.926,-4.923],[-54.926,4.923],[-54.886,4.939]],"c":true}]},{"t":67,"s":[{"i":[[0,0],[0,0],[0,0],[0,0]],"o":[[0,0],[0,0],[0,0],[0,0]],"v":[[54.926,-4.923],[-54.926,-4.923],[-54.926,4.923],[54.926,4.923]],"c":true}]}],"ix":2},"nm":"Path 1","mn":"ADBE Vector Shape - Group","hd":false},{"ty":"fl","c":{"a":0,"k":[1,1,1,1],"ix":4},"o":{"a":0,"k":100,"ix":5},"r":1,"bm":0,"nm":"Fill 1","mn":"ADBE Vector Graphic - Fill","hd":false},{"ty":"tr","p":{"a":0,"k":[0,60],"ix":2},"a":{"a":0,"k":[0,0],"ix":1},"s":{"a":0,"k":[100,100],"ix":3},"r":{"a":0,"k":0,"ix":6},"o":{"a":0,"k":100,"ix":7},"sk":{"a":0,"k":0,"ix":4},"sa":{"a":0,"k":0,"ix":5},"nm":"Transform"}],"nm":"Group 4","np":2,"cix":2,"bm":0,"ix":4,"mn":"ADBE Vector Group","hd":false},{"ty":"gr","it":[{"ind":0,"ty":"sh","ix":1,"ks":{"a":1,"k":[{"i":{"x":0.667,"y":1},"o":{"x":0.333,"y":0},"t":51,"s":[{"i":[[0,0],[0,0],[0,0],[0,0]],"o":[[0,0],[0,0],[0,0],[0,0]],"v":[[-54.886,-4.908],[-54.926,-4.923],[-54.926,4.923],[-54.886,4.939]],"c":true}]},{"t":65,"s":[{"i":[[0,0],[0,0],[0,0],[0,0]],"o":[[0,0],[0,0],[0,0],[0,0]],"v":[[54.926,-4.923],[-54.926,-4.923],[-54.926,4.923],[54.926,4.923]],"c":true}]}],"ix":2},"nm":"Path 1","mn":"ADBE Vector Shape - Group","hd":false},{"ty":"fl","c":{"a":0,"k":[1,1,1,1],"ix":4},"o":{"a":0,"k":100,"ix":5},"r":1,"bm":0,"nm":"Fill 1","mn":"ADBE Vector Graphic - Fill","hd":false},{"ty":"tr","p":{"a":0,"k":[0,40],"ix":2},"a":{"a":0,"k":[0,0],"ix":1},"s":{"a":0,"k":[100,100],"ix":3},"r":{"a":0,"k":0,"ix":6},"o":{"a":0,"k":100,"ix":7},"sk":{"a":0,"k":0,"ix":4},"sa":{"a":0,"k":0,"ix":5},"nm":"Transform"}],"nm":"Group 3","np":2,"cix":2,"bm":0,"ix":5,"mn":"ADBE Vector Group","hd":false},{"ty":"gr","it":[{"ind":0,"ty":"sh","ix":1,"ks":{"a":1,"k":[{"i":{"x":0.667,"y":1},"o":{"x":0.333,"y":0},"t":49,"s":[{"i":[[0,0],[0,0],[0,0],[0,0]],"o":[[0,0],[0,0],[0,0],[0,0]],"v":[[-54.886,-4.908],[-54.926,-4.923],[-54.926,4.923],[-54.886,4.939]],"c":true}]},{"t":63,"s":[{"i":[[0,0],[0,0],[0,0],[0,0]],"o":[[0,0],[0,0],[0,0],[0,0]],"v":[[54.926,-4.923],[-54.926,-4.923],[-54.926,4.923],[54.926,4.923]],"c":true}]}],"ix":2},"nm":"Path 1","mn":"ADBE Vector Shape - Group","hd":false},{"ty":"fl","c":{"a":0,"k":[1,1,1,1],"ix":4},"o":{"a":0,"k":100,"ix":5},"r":1,"bm":0,"nm":"Fill 1","mn":"ADBE Vector Graphic - Fill","hd":false},{"ty":"tr","p":{"a":0,"k":[0,20],"ix":2},"a":{"a":0,"k":[0,0],"ix":1},"s":{"a":0,"k":[100,100],"ix":3},"r":{"a":0,"k":0,"ix":6},"o":{"a":0,"k":100,"ix":7},"sk":{"a":0,"k":0,"ix":4},"sa":{"a":0,"k":0,"ix":5},"nm":"Transform"}],"nm":"Group 2","np":2,"cix":2,"bm":0,"ix":6,"mn":"ADBE Vector Group","hd":false},{"ty":"gr","it":[{"ind":0,"ty":"sh","ix":1,"ks":{"a":1,"k":[{"i":{"x":0.667,"y":1},"o":{"x":0.333,"y":0},"t":46,"s":[{"i":[[0,0],[0,0],[0,0],[0,0]],"o":[[0,0],[0,0],[0,0],[0,0]],"v":[[-54.886,-4.908],[-54.926,-4.923],[-54.926,4.923],[-54.886,4.939]],"c":true}]},{"t":60,"s":[{"i":[[0,0],[0,0],[0,0],[0,0]],"o":[[0,0],[0,0],[0,0],[0,0]],"v":[[54.926,-4.923],[-54.926,-4.923],[-54.926,4.923],[54.926,4.923]],"c":true}]}],"ix":2},"nm":"Path 1","mn":"ADBE Vector Shape - Group","hd":false},{"ty":"fl","c":{"a":0,"k":[1,1,1,1],"ix":4},"o":{"a":0,"k":100,"ix":5},"r":1,"bm":0,"nm":"Fill 1","mn":"ADBE Vector Graphic - Fill","hd":false},{"ty":"tr","p":{"a":0,"k":[0,0],"ix":2},"a":{"a":0,"k":[0,0],"ix":1},"s":{"a":0,"k":[100,100],"ix":3},"r":{"a":0,"k":0,"ix":6},"o":{"a":0,"k":100,"ix":7},"sk":{"a":0,"k":0,"ix":4},"sa":{"a":0,"k":0,"ix":5},"nm":"Transform"}],"nm":"Group 1","np":2,"cix":2,"bm":0,"ix":7,"mn":"ADBE Vector Group","hd":false}],"ip":46,"op":1200,"st":0,"bm":0},{"ddd":0,"ind":19,"ty":4,"nm":"Layer 4","sr":1,"ks":{"o":{"a":0,"k":100,"ix":11},"r":{"a":0,"k":0,"ix":10},"p":{"a":0,"k":[431.197,297.812,0],"ix":2},"a":{"a":0,"k":[-50.803,11.812,0],"ix":1},"s":{"a":0,"k":[100,100,100],"ix":6}},"ao":0,"shapes":[{"ty":"gr","it":[{"ind":0,"ty":"sh","ix":1,"ks":{"a":1,"k":[{"i":{"x":0.205,"y":1},"o":{"x":0.187,"y":0},"t":33,"s":[{"i":[[0,0],[0,0],[0,0],[0,0]],"o":[[0,0],[0,0],[0,0],[0,0]],"v":[[26.452,-78.365],[-128.059,-78.365],[-127.982,-78.386],[26.529,-78.386]],"c":true}]},{"t":78,"s":[{"i":[[0,0],[0,0],[0,0],[0,0]],"o":[[0,0],[0,0],[0,0],[0,0]],"v":[[26.452,-78.365],[-128.059,-78.365],[-128.059,101.989],[26.452,101.989]],"c":true}]}],"ix":2},"nm":"Path 1","mn":"ADBE Vector Shape - Group","hd":false},{"ty":"fl","c":{"a":0,"k":[0.686274528503,0.713725507259,1,1],"ix":4},"o":{"a":0,"k":100,"ix":5},"r":1,"bm":0,"nm":"Fill 1","mn":"ADBE Vector Graphic - Fill","hd":false},{"ty":"tr","p":{"a":0,"k":[0,0],"ix":2},"a":{"a":0,"k":[0,0],"ix":1},"s":{"a":0,"k":[100,100],"ix":3},"r":{"a":0,"k":0,"ix":6},"o":{"a":0,"k":100,"ix":7},"sk":{"a":0,"k":0,"ix":4},"sa":{"a":0,"k":0,"ix":5},"nm":"Transform"}],"nm":"Group 1","np":2,"cix":2,"bm":0,"ix":1,"mn":"ADBE Vector Group","hd":false}],"ip":32,"op":1200,"st":0,"bm":0},{"ddd":0,"ind":20,"ty":4,"nm":"Layer 3","sr":1,"ks":{"o":{"a":0,"k":100,"ix":11},"r":{"a":1,"k":[{"i":{"x":[0.833],"y":[0.833]},"o":{"x":[0.167],"y":[0.167]},"t":47,"s":[0]},{"t":649,"s":[132]}],"ix":10},"p":{"a":0,"k":[579.469,345.4,0],"ix":2},"a":{"a":0,"k":[97.469,59.4,0],"ix":1},"s":{"a":1,"k":[{"i":{"x":[0.667,0.667,0.667],"y":[1,1,1]},"o":{"x":[0.333,0.333,0.333],"y":[0,0,0]},"t":64,"s":[0,0,100]},{"t":82,"s":[100,100,100]}],"ix":6}},"ao":0,"shapes":[{"ty":"gr","it":[{"ind":0,"ty":"sh","ix":1,"ks":{"a":0,"k":{"i":[[1.108,0.002],[1.39,0.929],[0.639,1.544],[-0.327,1.639],[-1.183,1.181],[-1.639,0.324],[-1.543,-0.641],[-0.926,-1.39],[0.004,-1.671],[0.425,-1.024],[0.784,-0.783],[1.024,-0.422]],"o":[[-1.671,0],[-1.389,-0.928],[-0.639,-1.544],[0.327,-1.639],[1.182,-1.18],[1.639,-0.324],[1.543,0.642],[0.926,1.391],[0,1.108],[-0.424,1.024],[-0.785,0.783],[-1.025,0.423]],"v":[[97.445,67.838],[92.751,66.413],[89.641,62.621],[89.163,57.739],[91.479,53.415],[95.807,51.107],[100.688,51.594],[104.475,54.711],[105.89,59.408],[105.247,62.637],[103.416,65.374],[100.676,67.2]],"c":true},"ix":2},"nm":"Path 1","mn":"ADBE Vector Shape - Group","hd":false},{"ind":1,"ty":"sh","ix":2,"ks":{"a":0,"k":{"i":[[0,0],[0,0],[0,0],[1.044,1.73],[0,0],[0,0],[0,0],[1.959,0.478],[0,0],[0,0],[0,0],[1.722,-1.053],[0,0],[0,0],[0,0],[0.47,-1.967],[0,0],[0,0],[0,0],[-1.056,-1.726],[0,0],[0,0],[0,0],[-1.958,-0.481],[0,0],[0,0],[0,0],[-1.72,1.059],[0,0],[0,0],[0,0],[-0.513,1.985]],"o":[[0,0],[0,0],[-0.454,-1.97],[0,0],[0,0],[0,0],[-1.709,-1.071],[0,0],[0,0],[0,0],[-1.967,0.455],[0,0],[0,0],[0,0],[-1.078,1.711],[0,0],[0,0],[0,0],[0.452,1.972],[0,0],[0,0],[0,0],[1.71,1.069],[0,0],[0,0],[0,0],[1.968,-0.449],[0,0],[0,0],[0,0],[1.107,-1.725],[0,0]],"v":[[121.382,63.884],[121.382,55.116],[115.905,55.116],[113.644,49.532],[117.536,45.64],[111.382,39.486],[107.506,43.347],[101.968,41.009],[101.968,35.502],[93.138,35.502],[93.138,40.963],[87.569,43.24],[83.677,39.348],[77.524,45.501],[81.4,49.362],[79.062,54.916],[73.555,54.916],[73.555,63.684],[78.985,63.684],[81.262,69.268],[77.354,73.16],[83.508,79.314],[87.369,75.452],[92.907,77.791],[92.907,83.298],[101.691,83.298],[101.691,77.883],[107.26,75.606],[111.167,79.498],[117.32,73.345],[113.459,69.484],[115.905,63.884]],"c":true},"ix":2},"nm":"Path 2","mn":"ADBE Vector Shape - Group","hd":false},{"ty":"fl","c":{"a":0,"k":[0.482352942228,0.521568655968,0.988235294819,1],"ix":4},"o":{"a":0,"k":100,"ix":5},"r":1,"bm":0,"nm":"Fill 1","mn":"ADBE Vector Graphic - Fill","hd":false},{"ty":"tr","p":{"a":0,"k":[0,0],"ix":2},"a":{"a":0,"k":[0,0],"ix":1},"s":{"a":0,"k":[100,100],"ix":3},"r":{"a":0,"k":0,"ix":6},"o":{"a":0,"k":100,"ix":7},"sk":{"a":0,"k":0,"ix":4},"sa":{"a":0,"k":0,"ix":5},"nm":"Transform"}],"nm":"Group 1","np":3,"cix":2,"bm":0,"ix":1,"mn":"ADBE Vector Group","hd":false}],"ip":47,"op":1247,"st":47,"bm":0},{"ddd":0,"ind":21,"ty":4,"nm":"Layer 2","sr":1,"ks":{"o":{"a":0,"k":100,"ix":11},"r":{"a":1,"k":[{"i":{"x":[0.833],"y":[0.833]},"o":{"x":[0.167],"y":[0.167]},"t":47,"s":[0]},{"t":649,"s":[-132]}],"ix":10},"p":{"a":0,"k":[637.444,314.849,0],"ix":2},"a":{"a":0,"k":[155.444,28.849,0],"ix":1},"s":{"a":1,"k":[{"i":{"x":[0.667,0.667,0.667],"y":[1,1,1]},"o":{"x":[0.333,0.333,0.333],"y":[0,0,0]},"t":54,"s":[0,0,100]},{"t":72,"s":[100,100,100]}],"ix":6}},"ao":0,"shapes":[{"ty":"gr","it":[{"ind":0,"ty":"sh","ix":1,"ks":{"a":0,"k":{"i":[[3.154,0],[1.956,1.307],[0.9,2.173],[-0.459,2.306],[-1.663,1.663],[-2.307,0.459],[-2.172,-0.9],[-1.307,-1.955],[0,-2.352],[2.23,-2.23]],"o":[[-2.352,0],[-1.955,-1.307],[-0.9,-2.173],[0.459,-2.307],[1.663,-1.663],[2.307,-0.459],[2.173,0.9],[1.307,1.956],[0,3.153],[-2.23,2.23]],"v":[[155.367,40.825],[148.76,38.821],[144.381,33.484],[143.704,26.614],[146.958,20.525],[153.047,17.271],[159.917,17.948],[165.254,22.327],[167.258,28.934],[163.775,37.342]],"c":true},"ix":2},"nm":"Path 1","mn":"ADBE Vector Shape - Group","hd":false},{"ind":1,"ty":"sh","ix":2,"ks":{"a":0,"k":{"i":[[0,0],[0,0],[0,0],[1.482,2.431],[0,0],[0,0],[0,0],[2.766,0.665],[0,0],[0,0],[0,0],[2.424,-1.485],[0,0],[0,0],[0,0],[0.677,-2.763],[0,0],[0,0],[0,0],[-1.444,-2.473],[0,0],[0,0],[0,0],[-2.765,-0.669],[0,0],[0,0],[0,0],[-2.432,1.482],[0,0],[0,0],[0,0],[-0.667,2.766]],"o":[[0,0],[0,0],[-0.637,-2.776],[0,0],[0,0],[0,0],[-2.408,-1.515],[0,0],[0,0],[0,0],[-2.771,0.634],[0,0],[0,0],[0,0],[-1.504,2.415],[0,0],[0,0],[0,0],[0.583,2.804],[0,0],[0,0],[0,0],[2.411,1.511],[0,0],[0,0],[0,0],[2.775,-0.637],[0,0],[0,0],[0,0],[1.513,-2.41],[0,0]],"v":[[189.118,35.256],[189.118,22.95],[181.426,22.95],[178.226,15.089],[183.718,9.612],[174.965,0.859],[169.519,6.305],[161.705,3.013],[161.705,-4.879],[149.398,-4.879],[149.398,2.813],[141.553,6.013],[136.061,0.521],[127.308,9.274],[132.753,14.719],[129.461,22.534],[121.77,22.534],[121.77,34.841],[129.461,34.841],[132.522,42.809],[127.031,48.286],[135.784,57.039],[141.229,51.593],[149.044,54.885],[149.044,62.577],[161.351,62.577],[161.351,54.885],[169.212,51.686],[174.704,57.178],[183.441,48.424],[177.996,42.979],[181.288,35.164]],"c":true},"ix":2},"nm":"Path 2","mn":"ADBE Vector Shape - Group","hd":false},{"ty":"fl","c":{"a":0,"k":[0.482352942228,0.521568655968,0.988235294819,1],"ix":4},"o":{"a":0,"k":100,"ix":5},"r":1,"bm":0,"nm":"Fill 1","mn":"ADBE Vector Graphic - Fill","hd":false},{"ty":"tr","p":{"a":0,"k":[0,0],"ix":2},"a":{"a":0,"k":[0,0],"ix":1},"s":{"a":0,"k":[100,100],"ix":3},"r":{"a":0,"k":0,"ix":6},"o":{"a":0,"k":100,"ix":7},"sk":{"a":0,"k":0,"ix":4},"sa":{"a":0,"k":0,"ix":5},"nm":"Transform"}],"nm":"Group 1","np":3,"cix":2,"bm":0,"ix":1,"mn":"ADBE Vector Group","hd":false}],"ip":47,"op":1247,"st":47,"bm":0},{"ddd":0,"ind":22,"ty":4,"nm":"Layer 1","sr":1,"ks":{"o":{"a":0,"k":100,"ix":11},"r":{"a":1,"k":[{"i":{"x":[0.833],"y":[0.833]},"o":{"x":[0.167],"y":[0.167]},"t":47,"s":[0]},{"t":649,"s":[132]}],"ix":10},"p":{"a":0,"k":[569.631,265.03,0],"ix":2},"a":{"a":0,"k":[87.631,-20.97,0],"ix":1},"s":{"a":1,"k":[{"i":{"x":[0.667,0.667,0.667],"y":[1,1,1]},"o":{"x":[0.333,0.333,0.333],"y":[0,0,0]},"t":47,"s":[0,0,100]},{"t":65,"s":[100,100,100]}],"ix":6}},"ao":0,"shapes":[{"ty":"gr","it":[{"ind":0,"ty":"sh","ix":1,"ks":{"a":0,"k":{"i":[[4.007,0],[2.484,1.66],[1.143,2.76],[-0.583,2.93],[-2.113,2.112],[-2.93,0.583],[-2.76,-1.143],[-1.66,-2.484],[0,-2.988],[2.833,-2.833]],"o":[[-2.987,0],[-2.484,-1.66],[-1.143,-2.761],[0.583,-2.931],[2.112,-2.113],[2.931,-0.582],[2.761,1.144],[1.66,2.484],[0,4.006],[-2.833,2.834]],"v":[[87.631,-5.864],[79.239,-8.41],[73.675,-15.189],[72.815,-23.917],[76.95,-31.652],[84.684,-35.787],[93.412,-34.927],[100.192,-29.363],[102.738,-20.97],[98.313,-10.289]],"c":true},"ix":2},"nm":"Path 1","mn":"ADBE Vector Shape - Group","hd":false},{"ind":1,"ty":"sh","ix":2,"ks":{"a":0,"k":{"i":[[0,0],[0,0],[0,0],[1.885,3.08],[0,0],[0,0],[0,0],[3.515,0.847],[0,0],[0,0],[0,0],[3.092,-1.875],[0,0],[0,0],[0,0],[0.849,-3.509],[0,0],[0,0],[0,0],[-1.883,-3.089],[0,0],[0,0],[0,0],[-3.519,-0.87],[0,0],[0,0],[0,0],[-3.089,1.881],[0,0],[0,0],[0,0],[-0.852,3.509]],"o":[[0,0],[0,0],[-0.805,-3.521],[0,0],[0,0],[0,0],[-3.067,-1.915],[0,0],[0,0],[0,0],[-3.522,0.815],[0,0],[0,0],[0,0],[-1.912,3.063],[0,0],[0,0],[0,0],[0.816,3.524],[0,0],[0,0],[0,0],[3.062,1.941],[0,0],[0,0],[0,0],[3.524,-0.809],[0,0],[0,0],[0,0],[1.91,-3.063],[0,0]],"v":[[130.489,-12.94],[130.489,-28.662],[120.706,-28.662],[116.644,-38.63],[123.613,-45.599],[112.506,-56.721],[105.599,-49.799],[95.662,-53.968],[95.662,-63.844],[79.955,-63.844],[79.955,-54.106],[69.971,-50.045],[63.003,-57.014],[51.896,-45.891],[58.803,-38.984],[54.634,-29.062],[44.773,-29.062],[44.773,-13.34],[54.542,-13.34],[58.618,-3.356],[51.634,3.612],[62.757,14.719],[69.664,7.797],[79.601,12.042],[79.601,21.903],[95.308,21.903],[95.308,12.042],[105.292,7.981],[112.26,14.95],[123.367,3.843],[116.46,-3.08],[120.629,-13.002]],"c":true},"ix":2},"nm":"Path 2","mn":"ADBE Vector Shape - Group","hd":false},{"ty":"fl","c":{"a":0,"k":[0.482352942228,0.521568655968,0.988235294819,1],"ix":4},"o":{"a":0,"k":100,"ix":5},"r":1,"bm":0,"nm":"Fill 1","mn":"ADBE Vector Graphic - Fill","hd":false},{"ty":"tr","p":{"a":0,"k":[0,0],"ix":2},"a":{"a":0,"k":[0,0],"ix":1},"s":{"a":0,"k":[100,100],"ix":3},"r":{"a":0,"k":0,"ix":6},"o":{"a":0,"k":100,"ix":7},"sk":{"a":0,"k":0,"ix":4},"sa":{"a":0,"k":0,"ix":5},"nm":"Transform"}],"nm":"Group 1","np":3,"cix":2,"bm":0,"ix":1,"mn":"ADBE Vector Group","hd":false}],"ip":47,"op":1247,"st":47,"bm":0},{"ddd":0,"ind":23,"ty":4,"nm":"Merged Shape Layer","sr":1,"ks":{"o":{"a":0,"k":100,"ix":11},"r":{"a":0,"k":0,"ix":10},"p":{"a":0,"k":[503.315,470.645,0],"ix":2},"a":{"a":0,"k":[661.315,544.645,0],"ix":1},"s":{"a":1,"k":[{"i":{"x":[0,0,0.667],"y":[1,1,1]},"o":{"x":[0.142,0.142,0.333],"y":[0,0,0]},"t":0,"s":[0,0,100]},{"t":38,"s":[100,100,100]}],"ix":6}},"ao":0,"shapes":[{"ty":"gr","it":[{"ty":"gr","it":[{"ind":0,"ty":"sh","ix":1,"ks":{"a":0,"k":{"i":[[0,-2.448],[1.014,-1.518],[1.686,-0.698],[1.79,0.356],[1.291,1.29],[0.356,1.79],[-0.699,1.686],[-1.518,1.015],[-1.826,0],[-1.731,-1.731]],"o":[[0,1.826],[-1.014,1.518],[-1.687,0.699],[-1.791,-0.357],[-1.291,-1.291],[-0.356,-1.791],[0.699,-1.687],[1.517,-1.014],[2.447,0],[1.731,1.731]],"v":[[9.23,0],[7.674,5.128],[3.532,8.527],[-1.801,9.053],[-6.527,6.527],[-9.053,1.801],[-8.528,-3.532],[-5.128,-7.675],[0,-9.23],[6.526,-6.527]],"c":true},"ix":2},"nm":"Path 1","mn":"ADBE Vector Shape - Group","hd":false},{"ty":"fl","c":{"a":0,"k":[0.482352942228,0.521568655968,0.988235294819,1],"ix":4},"o":{"a":0,"k":100,"ix":5},"r":1,"bm":0,"nm":"Fill 1","mn":"ADBE Vector Graphic - Fill","hd":false},{"ty":"tr","p":{"a":0,"k":[0,0],"ix":2},"a":{"a":0,"k":[0,0],"ix":1},"s":{"a":0,"k":[100,100],"ix":3},"r":{"a":0,"k":0,"ix":6},"o":{"a":0,"k":100,"ix":7},"sk":{"a":0,"k":0,"ix":4},"sa":{"a":0,"k":0,"ix":5},"nm":"Transform"}],"nm":"Group 1","np":2,"cix":2,"bm":0,"ix":1,"mn":"ADBE Vector Group","hd":false},{"ty":"tr","p":{"a":0,"k":[661.293,524.523],"ix":2},"a":{"a":0,"k":[0,0],"ix":1},"s":{"a":0,"k":[100,100],"ix":3},"r":{"a":0,"k":0,"ix":6},"o":{"a":0,"k":100,"ix":7},"sk":{"a":0,"k":0,"ix":4},"sa":{"a":0,"k":0,"ix":5},"nm":"Transform"}],"nm":"Layer 4","np":1,"cix":2,"bm":0,"ix":1,"mn":"ADBE Vector Group","hd":false},{"ty":"gr","it":[{"ty":"gr","it":[{"ind":0,"ty":"sh","ix":1,"ks":{"a":0,"k":{"i":[[0,0],[0,0],[0,0],[0,0]],"o":[[0,0],[0,0],[0,0],[0,0]],"v":[[218.182,-116.137],[-218.183,-116.137],[-218.183,116.137],[218.182,116.137]],"c":true},"ix":2},"nm":"Path 1","mn":"ADBE Vector Shape - Group","hd":false},{"ty":"fl","c":{"a":0,"k":[1,1,1,1],"ix":4},"o":{"a":0,"k":100,"ix":5},"r":1,"bm":0,"nm":"Fill 1","mn":"ADBE Vector Graphic - Fill","hd":false},{"ty":"tr","p":{"a":0,"k":[0,0],"ix":2},"a":{"a":0,"k":[0,0],"ix":1},"s":{"a":0,"k":[100,100],"ix":3},"r":{"a":0,"k":0,"ix":6},"o":{"a":0,"k":100,"ix":7},"sk":{"a":0,"k":0,"ix":4},"sa":{"a":0,"k":0,"ix":5},"nm":"Transform"}],"nm":"Group 1","np":2,"cix":2,"bm":0,"ix":1,"mn":"ADBE Vector Group","hd":false},{"ty":"tr","p":{"a":0,"k":[661.331,371.266],"ix":2},"a":{"a":0,"k":[0,0],"ix":1},"s":{"a":0,"k":[100,100],"ix":3},"r":{"a":0,"k":0,"ix":6},"o":{"a":0,"k":100,"ix":7},"sk":{"a":0,"k":0,"ix":4},"sa":{"a":0,"k":0,"ix":5},"nm":"Transform"}],"nm":"Layer 3","np":1,"cix":2,"bm":0,"ix":2,"mn":"ADBE Vector Group","hd":false},{"ty":"gr","it":[{"ty":"gr","it":[{"ind":0,"ty":"sh","ix":1,"ks":{"a":0,"k":{"i":[[0,0],[0,0],[0,0],[3.644,-3.301],[5.153,0],[0,0],[3.64,3.301],[0,4.665]],"o":[[0,0],[0,0],[0,4.668],[-3.644,3.301],[0,0],[-5.151,-0.004],[-3.64,-3.3],[0,0]],"v":[[-235.557,-20.452],[235.557,-20.452],[235.557,2.851],[229.867,15.297],[216.128,20.452],[-216.143,20.452],[-229.872,15.292],[-235.557,2.851]],"c":true},"ix":2},"nm":"Path 1","mn":"ADBE Vector Shape - Group","hd":false},{"ty":"fl","c":{"a":0,"k":[0.588235318661,0.61960786581,1,1],"ix":4},"o":{"a":0,"k":100,"ix":5},"r":1,"bm":0,"nm":"Fill 1","mn":"ADBE Vector Graphic - Fill","hd":false},{"ty":"tr","p":{"a":0,"k":[0,0],"ix":2},"a":{"a":0,"k":[0,0],"ix":1},"s":{"a":0,"k":[100,100],"ix":3},"r":{"a":0,"k":0,"ix":6},"o":{"a":0,"k":100,"ix":7},"sk":{"a":0,"k":0,"ix":4},"sa":{"a":0,"k":0,"ix":5},"nm":"Transform"}],"nm":"Group 1","np":2,"cix":2,"bm":0,"ix":1,"mn":"ADBE Vector Group","hd":false},{"ty":"tr","p":{"a":0,"k":[661.315,524.193],"ix":2},"a":{"a":0,"k":[0,0],"ix":1},"s":{"a":0,"k":[100,100],"ix":3},"r":{"a":0,"k":0,"ix":6},"o":{"a":0,"k":100,"ix":7},"sk":{"a":0,"k":0,"ix":4},"sa":{"a":0,"k":0,"ix":5},"nm":"Transform"}],"nm":"Layer 2","np":1,"cix":2,"bm":0,"ix":3,"mn":"ADBE Vector Group","hd":false},{"ty":"gr","it":[{"ty":"gr","it":[{"ind":0,"ty":"sh","ix":1,"ks":{"a":0,"k":{"i":[[-5.173,0],[0,0],[-3.658,-3.659],[0,-5.173],[0,0],[0,0],[0,0],[-3.658,3.658]],"o":[[0,0],[5.173,0],[3.658,3.658],[0,0],[0,0],[0,0],[0,-5.173],[3.658,-3.659]],"v":[[-216.051,-131.92],[216.052,-131.92],[229.844,-126.206],[235.557,-112.414],[235.557,131.92],[-235.557,131.92],[-235.557,-112.414],[-229.844,-126.206]],"c":true},"ix":2},"nm":"Path 1","mn":"ADBE Vector Shape - Group","hd":false},{"ty":"fl","c":{"a":0,"k":[0.482352942228,0.521568655968,0.988235294819,1],"ix":4},"o":{"a":0,"k":100,"ix":5},"r":1,"bm":0,"nm":"Fill 1","mn":"ADBE Vector Graphic - Fill","hd":false},{"ty":"tr","p":{"a":0,"k":[0,0],"ix":2},"a":{"a":0,"k":[0,0],"ix":1},"s":{"a":0,"k":[100,100],"ix":3},"r":{"a":0,"k":0,"ix":6},"o":{"a":0,"k":100,"ix":7},"sk":{"a":0,"k":0,"ix":4},"sa":{"a":0,"k":0,"ix":5},"nm":"Transform"}],"nm":"Group 1","np":2,"cix":2,"bm":0,"ix":1,"mn":"ADBE Vector Group","hd":false},{"ty":"tr","p":{"a":0,"k":[661.315,371.82],"ix":2},"a":{"a":0,"k":[0,0],"ix":1},"s":{"a":0,"k":[100,100],"ix":3},"r":{"a":0,"k":0,"ix":6},"o":{"a":0,"k":100,"ix":7},"sk":{"a":0,"k":0,"ix":4},"sa":{"a":0,"k":0,"ix":5},"nm":"Transform"}],"nm":"Layer 1","np":1,"cix":2,"bm":0,"ix":4,"mn":"ADBE Vector Group","hd":false}],"ip":0,"op":1200,"st":0,"bm":0},{"ddd":0,"ind":24,"ty":4,"nm":"Layer 6","sr":1,"ks":{"o":{"a":0,"k":100,"ix":11},"r":{"a":0,"k":0,"ix":10},"p":{"a":0,"k":[470.46,494.679,0],"ix":2},"a":{"a":0,"k":[0,0,0],"ix":1},"s":{"a":0,"k":[100,100,100],"ix":6}},"ao":0,"shapes":[{"ty":"gr","it":[{"ind":0,"ty":"sh","ix":1,"ks":{"a":0,"k":{"i":[[0,0],[0,0],[0,0],[0,0],[0,0],[0,0]],"o":[[0,0],[0,0],[0,0],[0,0],[0,0],[0,0]],"v":[[-85.835,-38.55],[-85.835,4.217],[-2.71,4.217],[-2.71,41.562],[85.835,41.562],[85.835,-41.562]],"c":false},"ix":2},"nm":"Path 1","mn":"ADBE Vector Shape - Group","hd":false},{"ty":"st","c":{"a":0,"k":[0.721568627451,0.741176470588,1,1],"ix":3},"o":{"a":0,"k":100,"ix":4},"w":{"a":0,"k":2,"ix":5},"lc":1,"lj":1,"ml":4,"bm":0,"d":[{"n":"d","nm":"dash","v":{"a":0,"k":10,"ix":1}},{"n":"o","nm":"offset","v":{"a":1,"k":[{"i":{"x":[0.833],"y":[0.833]},"o":{"x":[0.167],"y":[0.167]},"t":0,"s":[0]},{"t":599,"s":[-381]}],"ix":7}}],"nm":"Stroke 1","mn":"ADBE Vector Graphic - Stroke","hd":false},{"ty":"tr","p":{"a":0,"k":[0,0],"ix":2},"a":{"a":0,"k":[0,0],"ix":1},"s":{"a":0,"k":[100,100],"ix":3},"r":{"a":0,"k":0,"ix":6},"o":{"a":0,"k":100,"ix":7},"sk":{"a":0,"k":0,"ix":4},"sa":{"a":0,"k":0,"ix":5},"nm":"Transform"}],"nm":"Group 1","np":2,"cix":2,"bm":0,"ix":1,"mn":"ADBE Vector Group","hd":false},{"ty":"tm","s":{"a":0,"k":0,"ix":1},"e":{"a":1,"k":[{"i":{"x":[0.833],"y":[0.833]},"o":{"x":[0.167],"y":[0.167]},"t":71,"s":[0]},{"t":128,"s":[100]}],"ix":2},"o":{"a":0,"k":0,"ix":3},"m":1,"ix":2,"nm":"Trim Paths 1","mn":"ADBE Vector Filter - Trim","hd":false}],"ip":0,"op":1200,"st":0,"bm":0}],"markers":[]}